[
    {
        "id": "0e992f61a706eb58",
        "type": "tab",
        "label": "Grove Pi 1",
        "disabled": false,
        "info": "",
        "env": []
    },
    {
        "id": "5cc691194be3a9d8",
        "type": "group",
        "z": "0e992f61a706eb58",
        "style": {
            "stroke": "#999999",
            "stroke-opacity": "1",
            "fill": "none",
            "fill-opacity": "1",
            "label": true,
            "label-position": "nw",
            "color": "#a4a4a4"
        },
        "nodes": [
            "5e1791bb4713a3ce",
            "1e6ecf529f287354",
            "1ca53671077d195c",
            "aa85db266027c50e",
            "dfaa92d4dd849eab",
            "75f65aa6282bdbfe",
            "c493a96ad53dfc0d",
            "38d9086a2977fa73",
            "459424595753cf62",
            "e16a31d51c76621e",
            "2ceda20c5bfc9df6",
            "76f49feef62a3798"
        ],
        "x": 28,
        "y": 19,
        "w": 1264,
        "h": 988
    },
    {
        "id": "73bca6c267ce7e72",
        "type": "group",
        "z": "0e992f61a706eb58",
        "style": {
            "stroke": "#999999",
            "stroke-opacity": "1",
            "fill": "none",
            "fill-opacity": "1",
            "label": true,
            "label-position": "nw",
            "color": "#a4a4a4"
        },
        "nodes": [
            "aa04da7c9300617c",
            "6229e595b7e29330",
            "0608b5f4d7a72b5a",
            "be9c8d8a9e47d8d2"
        ],
        "x": 1308,
        "y": 19,
        "w": 744,
        "h": 508
    },
    {
        "id": "c07101037867795b",
        "type": "group",
        "z": "0e992f61a706eb58",
        "style": {
            "stroke": "#999999",
            "stroke-opacity": "1",
            "fill": "none",
            "fill-opacity": "1",
            "label": true,
            "label-position": "nw",
            "color": "#a4a4a4"
        },
        "nodes": [
            "c49bc9415318b8c4",
            "93149a58644b3b8a",
            "b504de31678f72cd",
            "aad72eeb907091b5"
        ],
        "x": 1308,
        "y": 539,
        "w": 1284,
        "h": 428
    },
    {
        "id": "ef1e886f28df8d51",
        "type": "group",
        "z": "0e992f61a706eb58",
        "style": {
            "stroke": "#999999",
            "stroke-opacity": "1",
            "fill": "none",
            "fill-opacity": "1",
            "label": true,
            "label-position": "nw",
            "color": "#a4a4a4"
        },
        "nodes": [
            "3815a81333d53168",
            "71c8aa3b6b346885",
            "c3bc344f2852449d",
            "7404463c72010353",
            "6d15c9fd9f5b6e7e",
            "2dc032b30fb2cdf3",
            "ce7e83e4ad2de9f6"
        ],
        "x": 28,
        "y": 1019,
        "w": 1364,
        "h": 568
    },
    {
        "id": "dfaa92d4dd849eab",
        "type": "group",
        "z": "0e992f61a706eb58",
        "g": "5cc691194be3a9d8",
        "style": {
            "stroke": "#999999",
            "stroke-opacity": "1",
            "fill": "none",
            "fill-opacity": "1",
            "label": true,
            "label-position": "nw",
            "color": "#a4a4a4"
        },
        "nodes": [
            "6207ffa8f84e5c6a",
            "0b0a2730b9605d76",
            "0b878342b55230f2"
        ],
        "x": 54,
        "y": 79,
        "w": 452,
        "h": 122
    },
    {
        "id": "75f65aa6282bdbfe",
        "type": "group",
        "z": "0e992f61a706eb58",
        "g": "5cc691194be3a9d8",
        "style": {
            "stroke": "#999999",
            "stroke-opacity": "1",
            "fill": "none",
            "fill-opacity": "1",
            "label": true,
            "label-position": "nw",
            "color": "#a4a4a4"
        },
        "nodes": [
            "d9d56f37ce6d5202",
            "4bcc2a14d33814a7",
            "8d451422dd375d1d",
            "3e7c290b44363b6b",
            "511e97e419be5a46"
        ],
        "x": 54,
        "y": 219,
        "w": 872,
        "h": 137
    },
    {
        "id": "c493a96ad53dfc0d",
        "type": "group",
        "z": "0e992f61a706eb58",
        "g": "5cc691194be3a9d8",
        "style": {
            "stroke": "#999999",
            "stroke-opacity": "1",
            "fill": "none",
            "fill-opacity": "1",
            "label": true,
            "label-position": "nw",
            "color": "#a4a4a4"
        },
        "nodes": [
            "2f017fb9807f908a",
            "ea91053b0fb8900e",
            "1f6857ce7e2b2c23",
            "dda0923130ab8939"
        ],
        "x": 54,
        "y": 379,
        "w": 672,
        "h": 122
    },
    {
        "id": "38d9086a2977fa73",
        "type": "group",
        "z": "0e992f61a706eb58",
        "g": "5cc691194be3a9d8",
        "style": {
            "stroke": "#999999",
            "stroke-opacity": "1",
            "fill": "none",
            "fill-opacity": "1",
            "label": true,
            "label-position": "nw",
            "color": "#a4a4a4"
        },
        "nodes": [
            "463673ed19baf5d9",
            "f6fe70541e8bda69",
            "ce0dd89034e3f85a",
            "e85567546df25f38",
            "0b351037472e36e4"
        ],
        "x": 54,
        "y": 519,
        "w": 952,
        "h": 137
    },
    {
        "id": "459424595753cf62",
        "type": "group",
        "z": "0e992f61a706eb58",
        "g": "5cc691194be3a9d8",
        "style": {
            "stroke": "#999999",
            "stroke-opacity": "1",
            "fill": "none",
            "fill-opacity": "1",
            "label": true,
            "label-position": "nw",
            "color": "#a4a4a4"
        },
        "nodes": [
            "8d5ceb9a904f3503",
            "eb78f533eb9a17d3",
            "b3ecbf97c400be84",
            "65f4a64fb60f38bc",
            "6f855d6da668d3ef"
        ],
        "x": 54,
        "y": 679,
        "w": 1052,
        "h": 137
    },
    {
        "id": "6229e595b7e29330",
        "type": "group",
        "z": "0e992f61a706eb58",
        "g": "73bca6c267ce7e72",
        "style": {
            "stroke": "#999999",
            "stroke-opacity": "1",
            "fill": "none",
            "fill-opacity": "1",
            "label": true,
            "label-position": "nw",
            "color": "#a4a4a4"
        },
        "nodes": [
            "8692d60c3afac9ea",
            "e0185a457c0f36cb",
            "be6b498ae29ffb92",
            "d1221e354410fc66",
            "500ce2f7ea2429e1"
        ],
        "x": 1334,
        "y": 79,
        "w": 692,
        "h": 142
    },
    {
        "id": "0608b5f4d7a72b5a",
        "type": "group",
        "z": "0e992f61a706eb58",
        "g": "73bca6c267ce7e72",
        "style": {
            "stroke": "#999999",
            "stroke-opacity": "1",
            "fill": "none",
            "fill-opacity": "1",
            "label": true,
            "label-position": "nw",
            "color": "#a4a4a4"
        },
        "nodes": [
            "03a7735eb8d49cc1",
            "abd2ccc7d536c490",
            "bf5c2108be768111",
            "6071d58d4a545640"
        ],
        "x": 1334,
        "y": 239,
        "w": 622,
        "h": 122
    },
    {
        "id": "be9c8d8a9e47d8d2",
        "type": "group",
        "z": "0e992f61a706eb58",
        "g": "73bca6c267ce7e72",
        "style": {
            "stroke": "#999999",
            "stroke-opacity": "1",
            "fill": "none",
            "fill-opacity": "1",
            "label": true,
            "label-position": "nw",
            "color": "#a4a4a4"
        },
        "nodes": [
            "046dc45923aa5596",
            "72306b47b1bb7e82",
            "aea31bc84326236c",
            "672abb38db405708"
        ],
        "x": 1334,
        "y": 379,
        "w": 652,
        "h": 122
    },
    {
        "id": "93149a58644b3b8a",
        "type": "group",
        "z": "0e992f61a706eb58",
        "g": "c07101037867795b",
        "style": {
            "stroke": "#999999",
            "stroke-opacity": "1",
            "fill": "none",
            "fill-opacity": "1",
            "label": true,
            "label-position": "nw",
            "color": "#a4a4a4"
        },
        "nodes": [
            "45716de8bb60743b",
            "c2c555de1b5b0a6c",
            "2c91b78b561f1c10",
            "5921bbfc575a0b88",
            "9c0cfaf36b5bffab"
        ],
        "x": 1334,
        "y": 599,
        "w": 1012,
        "h": 122
    },
    {
        "id": "b504de31678f72cd",
        "type": "group",
        "z": "0e992f61a706eb58",
        "g": "c07101037867795b",
        "style": {
            "stroke": "#999999",
            "stroke-opacity": "1",
            "fill": "none",
            "fill-opacity": "1",
            "label": true,
            "label-position": "nw",
            "color": "#a4a4a4"
        },
        "nodes": [
            "98eba2328ce0078a",
            "ced47629dad00272"
        ],
        "x": 1334,
        "y": 739,
        "w": 212,
        "h": 122
    },
    {
        "id": "aad72eeb907091b5",
        "type": "group",
        "z": "0e992f61a706eb58",
        "g": "c07101037867795b",
        "style": {
            "stroke": "#999999",
            "stroke-opacity": "1",
            "fill": "none",
            "fill-opacity": "1",
            "label": true,
            "label-position": "nw",
            "color": "#a4a4a4"
        },
        "nodes": [
            "e339ee3e7f926e14",
            "d937a38c42b348c3",
            "166ec84d0479edca",
            "87c6979873121a16",
            "1ba6a00a59d90dd3",
            "c94b4efcf259fe8d",
            "be754b1a8f482a59",
            "fe92c5eaa6430a56",
            "e56f211f1a234d45",
            "f3b5737469a0ae23"
        ],
        "x": 1574,
        "y": 739,
        "w": 992,
        "h": 202
    },
    {
        "id": "71c8aa3b6b346885",
        "type": "group",
        "z": "0e992f61a706eb58",
        "g": "ef1e886f28df8d51",
        "style": {
            "stroke": "#999999",
            "stroke-opacity": "1",
            "fill": "none",
            "fill-opacity": "1",
            "label": true,
            "label-position": "nw",
            "color": "#a4a4a4"
        },
        "nodes": [
            "8a85e827a930f392",
            "f5dc23973c30ac07",
            "dc73d130ee96e626",
            "03ad7b18a394a83b",
            "b98f28c74f086922"
        ],
        "x": 54,
        "y": 1079,
        "w": 512,
        "h": 169.5
    },
    {
        "id": "c3bc344f2852449d",
        "type": "group",
        "z": "0e992f61a706eb58",
        "g": "ef1e886f28df8d51",
        "style": {
            "stroke": "#999999",
            "stroke-opacity": "1",
            "fill": "none",
            "fill-opacity": "1",
            "label": true,
            "label-position": "nw",
            "color": "#a4a4a4"
        },
        "nodes": [
            "8900cf9202efbd7a",
            "f9d162e9615d1636",
            "73598425fff63a7b",
            "faa613d260876a51",
            "52c952ec42fbd7ca"
        ],
        "x": 594,
        "y": 1079,
        "w": 612,
        "h": 162
    },
    {
        "id": "7404463c72010353",
        "type": "group",
        "z": "0e992f61a706eb58",
        "g": "ef1e886f28df8d51",
        "style": {
            "stroke": "#999999",
            "stroke-opacity": "1",
            "fill": "none",
            "fill-opacity": "1",
            "label": true,
            "label-position": "nw",
            "color": "#a4a4a4"
        },
        "nodes": [
            "9920a4a96963e478",
            "9932d1a9eb8e9e30",
            "b5f96ecabad2153e",
            "8cae70e72de3e1f6"
        ],
        "x": 54,
        "y": 1259,
        "w": 572,
        "h": 122
    },
    {
        "id": "6d15c9fd9f5b6e7e",
        "type": "group",
        "z": "0e992f61a706eb58",
        "g": "ef1e886f28df8d51",
        "style": {
            "stroke": "#999999",
            "stroke-opacity": "1",
            "fill": "none",
            "fill-opacity": "1",
            "label": true,
            "label-position": "nw",
            "color": "#a4a4a4"
        },
        "nodes": [
            "a2e2b9722d48755b",
            "fe886807dd77d494",
            "b213f336912bac3c",
            "25c59be20820f116",
            "7570e2d0c0bc7666",
            "0ee56e928c0e6155",
            "93a285a031db5877",
            "ad1c7710ab01be2b"
        ],
        "x": 654,
        "y": 1259,
        "w": 712,
        "h": 162
    },
    {
        "id": "2ceda20c5bfc9df6",
        "type": "group",
        "z": "0e992f61a706eb58",
        "g": "5cc691194be3a9d8",
        "style": {
            "stroke": "#999999",
            "stroke-opacity": "1",
            "fill": "none",
            "fill-opacity": "1",
            "label": true,
            "label-position": "nw",
            "color": "#a4a4a4"
        },
        "nodes": [
            "6426a2171f12d72f",
            "0b3b7672f6522f91",
            "86b8ac629d80c35d",
            "2d7dc0470413a8de"
        ],
        "x": 534,
        "y": 79,
        "w": 732,
        "h": 122
    },
    {
        "id": "76f49feef62a3798",
        "type": "group",
        "z": "0e992f61a706eb58",
        "g": "5cc691194be3a9d8",
        "style": {
            "stroke": "#999999",
            "stroke-opacity": "1",
            "fill": "none",
            "fill-opacity": "1",
            "label": true,
            "label-position": "nw",
            "color": "#a4a4a4"
        },
        "nodes": [
            "977de577e811690b",
            "fdae73bae71188f3",
            "b8e4c175ebf1cbce",
            "1b3d7b866bb8db1a",
            "ca2f6d1e9ece927b",
            "e18476dae9472cd5"
        ],
        "x": 54,
        "y": 839,
        "w": 972,
        "h": 142
    },
    {
        "id": "ce7e83e4ad2de9f6",
        "type": "group",
        "z": "0e992f61a706eb58",
        "g": "ef1e886f28df8d51",
        "style": {
            "stroke": "#999999",
            "stroke-opacity": "1",
            "fill": "none",
            "fill-opacity": "1",
            "label": true,
            "label-position": "nw",
            "color": "#a4a4a4"
        },
        "nodes": [
            "b0cba382c50d09ab",
            "6394a83cef5e60d3",
            "4f64cea803c823d3",
            "e82b7cfb18701fc0"
        ],
        "x": 374,
        "y": 1439,
        "w": 732,
        "h": 122
    },
    {
        "id": "2dc032b30fb2cdf3",
        "type": "group",
        "z": "0e992f61a706eb58",
        "g": "ef1e886f28df8d51",
        "style": {
            "stroke": "#999999",
            "stroke-opacity": "1",
            "fill": "none",
            "fill-opacity": "1",
            "label": true,
            "label-position": "nw",
            "color": "#a4a4a4"
        },
        "nodes": [
            "4fa12711f176e1bb",
            "dedbe14c1df4bd31",
            "e977007d93a70419"
        ],
        "x": 54,
        "y": 1399,
        "w": 312,
        "h": 122
    },
    {
        "id": "ddbc521e6b96d5b1",
        "type": "group",
        "z": "0e992f61a706eb58",
        "g": "9379380a7711d644",
        "style": {
            "stroke": "#999999",
            "stroke-opacity": "1",
            "fill": "none",
            "fill-opacity": "1",
            "label": true,
            "label-position": "nw",
            "color": "#a4a4a4"
        },
        "nodes": [
            "3f49b68e543d0680",
            "fa89397cc634bc5a",
            "7baa995010645c42",
            "2c583a3f351f9514",
            "fbd399cdde11bdfe",
            "2e682f79be89001d"
        ],
        "x": 1434,
        "y": 1039,
        "w": 1192,
        "h": 122
    },
    {
        "id": "3053a935888cd15a",
        "type": "group",
        "z": "0e992f61a706eb58",
        "g": "9379380a7711d644",
        "style": {
            "stroke": "#999999",
            "stroke-opacity": "1",
            "fill": "none",
            "fill-opacity": "1",
            "label": true,
            "label-position": "nw",
            "color": "#a4a4a4"
        },
        "nodes": [
            "af72f5122aab46ee",
            "ea3ea16e0f56fd3f",
            "a288150cbe49f92f",
            "eccc694b470a9fd3",
            "5df517086efdfe47",
            "ba19471e9916b696"
        ],
        "x": 1434,
        "y": 1179,
        "w": 1172,
        "h": 122
    },
    {
        "id": "d6f33d740f37f66b",
        "type": "group",
        "z": "0e992f61a706eb58",
        "g": "9379380a7711d644",
        "style": {
            "stroke": "#999999",
            "stroke-opacity": "1",
            "fill": "none",
            "fill-opacity": "1",
            "label": true,
            "label-position": "nw",
            "color": "#a4a4a4"
        },
        "nodes": [
            "ea1ba8dc9c893984",
            "a95d6e9cb54b0e9e",
            "dbb8f9c1e900f0d1",
            "4f97c6f6862eb0f4"
        ],
        "x": 1434,
        "y": 1319,
        "w": 752,
        "h": 122
    },
    {
        "id": "9379380a7711d644",
        "type": "group",
        "z": "0e992f61a706eb58",
        "style": {
            "stroke": "#999999",
            "stroke-opacity": "1",
            "fill": "none",
            "fill-opacity": "1",
            "label": true,
            "label-position": "nw",
            "color": "#a4a4a4"
        },
        "nodes": [
            "d6f33d740f37f66b",
            "3053a935888cd15a",
            "ddbc521e6b96d5b1",
            "0299c5d668ee9060"
        ],
        "x": 1408,
        "y": 979,
        "w": 1244,
        "h": 488
    },
    {
        "id": "mqtt_broker_pi1",
        "type": "mqtt-broker",
        "name": "Pi1 Mosquitto",
        "broker": "127.0.0.1",
        "port": "1883",
        "clientid": "autoguard-pi1",
        "autoConnect": true,
        "usetls": false,
        "protocolVersion": "4",
        "keepalive": "60",
        "cleansession": true,
        "autoUnsubscribe": true,
        "birthTopic": "autoguard/pi1/online",
        "birthQos": "1",
        "birthPayload": "{\"online\":true}",
        "birthMsg": {},
        "closeTopic": "autoguard/pi1/online",
        "closeQos": "1",
        "closePayload": "{\"online\":false}",
        "closeMsg": {},
        "willTopic": "autoguard/pi1/online",
        "willQos": "1",
        "willPayload": "{\"online\":false}",
        "willMsg": {},
        "userProps": "",
        "sessionExpiry": ""
    },
    {
        "id": "influx_cfg_pi1",
        "type": "influxdb",
        "hostname": "127.0.0.1",
        "port": "8086",
        "protocol": "http",
        "database": "autoguard",
        "name": "InfluxDB (Pi1)",
        "usetls": false,
        "tls": "",
        "influxdbVersion": "1.x"
    },
    {
        "id": "fdb931804d668213",
        "type": "ui-base",
        "name": "My Dashboard",
        "path": "/dashboard",
        "appIcon": "",
        "includeClientData": true,
        "acceptsClientConfig": [
            "ui-notification",
            "ui-control"
        ],
        "showPathInSidebar": false,
        "headerContent": "page",
        "navigationStyle": "default",
        "titleBarStyle": "default",
        "showReconnectNotification": true,
        "notificationDisplayTime": 1,
        "showDisconnectNotification": true,
        "allowInstall": false
    },
    {
        "id": "0b3be90bb51f745f",
        "type": "ui-theme",
        "name": "Default Theme",
        "colors": {
            "surface": "#ffffff",
            "primary": "#0094CE",
            "bgPage": "#eeeeee",
            "groupBg": "#ffffff",
            "groupOutline": "#cccccc"
        },
        "sizes": {
            "density": "default",
            "pagePadding": "12px",
            "groupGap": "12px",
            "groupBorderRadius": "4px",
            "widgetGap": "12px"
        }
    },
    {
        "id": "65ed57ceb91b65f7",
        "type": "ui-page",
        "name": "Page 1",
        "ui": "fdb931804d668213",
        "path": "/page1",
        "icon": "home",
        "layout": "grid",
        "theme": "0b3be90bb51f745f",
        "breakpoints": [
            {
                "name": "Default",
                "px": 0,
                "cols": 3
            },
            {
                "name": "Tablet",
                "px": 576,
                "cols": 6
            },
            {
                "name": "Small Desktop",
                "px": 768,
                "cols": 9
            },
            {
                "name": "Desktop",
                "px": 1024,
                "cols": 12
            }
        ],
        "order": 1,
        "className": "",
        "visible": "true",
        "disabled": "false"
    },
    {
        "id": "b3989f4e62321598",
        "type": "ui-group",
        "name": "Group 1",
        "page": "65ed57ceb91b65f7",
        "width": 6,
        "height": 1,
        "order": 1,
        "showTitle": true,
        "className": "",
        "visible": true,
        "disabled": false,
        "groupType": "default"
    },
    {
        "id": "0b0a2730b9605d76",
        "type": "inject",
        "z": "0e992f61a706eb58",
        "g": "dfaa92d4dd849eab",
        "name": "Start Device",
        "props": [],
        "repeat": "",
        "crontab": "",
        "once": true,
        "onceDelay": 0.1,
        "topic": "",
        "x": 170,
        "y": 160,
        "wires": [
            [
                "0b878342b55230f2"
            ]
        ]
    },
    {
        "id": "0b878342b55230f2",
        "type": "function",
        "z": "0e992f61a706eb58",
        "g": "dfaa92d4dd849eab",
        "name": "Initialize System State",
        "func": "/**\n * Initialize all shared state used by GrovePi 1.\n * This node should run once on startup.\n */\nconst now = Date.now();\n\nconst defaults = {\n    armed: false,\n    securityState: \"inactive\", // inactive | active | suspicious | alarm | resolved\n    resolvedUntil: null,\n    settings: {\n        suspiciousModeEnabled: true,\n        seatDeltaCm: 10,\n        seatDebounceMs: 1200,\n        vibrationSpike: 1,\n        accelMagSpike: 1.8,\n        confirmWindowMs: 4000,\n        suspiciousTimeoutMs: 60000,\n        alarmMinMs: 15000,\n        autoResolveQuietMs: 6000,\n        notificationPhone: \"\",\n        notificationEmail: \"\"\n    },\n    baseline: {\n        distanceCm: null,\n        capturedAt: null\n    },\n    last: {\n        distanceCm: null,\n        distanceAt: null,\n        temperatureC: null,\n        humidity: null,\n        climateAt: null,\n        vibration: null,\n        vibrationAt: null,\n        accelMag: null,\n        accelAt: null\n    },\n    intrusion: {\n        id: null,\n        startedAt: null,\n        lastEvidenceAt: null,\n        confirmedBy: [],\n        status: \"closed\",\n        picturePath: null,\n        videoPath: null,\n        videoActive: false,\n        note: null,\n        closedAt: null\n    },\n    alarm: {\n        active: false,\n        tickCount: 0,\n        ledState: 0\n    },\n    liveFeedEvents: [],\n    seatStableSince: null\n};\n\nfor (const [key, value] of Object.entries(defaults)) {\n    if (flow.get(key) === undefined) {\n        flow.set(key, value);\n    }\n}\n\nnode.status({\n    fill: \"grey\",\n    shape: \"dot\",\n    text: `armed=${flow.get(\"armed\")} state=${flow.get(\"securityState\")}`\n});\n\nmsg.payload = {\n    ok: true,\n    armed: flow.get(\"armed\"),\n    state: flow.get(\"securityState\"),\n    ts: now\n};\n\nreturn msg;",
        "outputs": 1,
        "timeout": 0,
        "noerr": 0,
        "initialize": "",
        "finalize": "",
        "libs": [],
        "x": 380,
        "y": 160,
        "wires": [
            []
        ]
    },
    {
        "id": "d9d56f37ce6d5202",
        "type": "http in",
        "z": "0e992f61a706eb58",
        "g": "75f65aa6282bdbfe",
        "name": "POST /api/arm",
        "url": "/api/arm",
        "method": "post",
        "upload": false,
        "skipBodyParsing": false,
        "swaggerDoc": "",
        "x": 160,
        "y": 300,
        "wires": [
            [
                "3e7c290b44363b6b"
            ]
        ]
    },
    {
        "id": "4bcc2a14d33814a7",
        "type": "function",
        "z": "0e992f61a706eb58",
        "g": "75f65aa6282bdbfe",
        "name": "Handle Arm Request",
        "func": "/**\n * Arm or disarm the system.\n * When arming, the baseline is cleared and recaptured from the latest ultrasonic reading.\n * When disarming, any active alarm devices are explicitly shut down.\n * Preserves the original HTTP message for the http response node.\n */\nconst now = Date.now();\nconst body = msg.payload || {};\nconst armed = Boolean(body.armed);\n\nflow.set(\"armed\", armed);\nflow.set(\"seatStableSince\", null);\nflow.set(\"resolvedUntil\", null);\n\nlet alarmControlMsg = null;\n\nif (!armed) {\n    flow.set(\"securityState\", \"inactive\");\n    flow.set(\"baseline\", { distanceCm: null, capturedAt: null });\n    flow.set(\"intrusion\", {\n        id: null,\n        startedAt: null,\n        lastEvidenceAt: null,\n        confirmedBy: [],\n        status: \"closed\",\n        picturePath: null,\n        videoPath: null,\n        videoActive: false,\n        note: null,\n        closedAt: now\n    });\n    flow.set(\"alarm\", { active: false, tickCount: 0, ledState: 0 });\n\n    alarmControlMsg = RED.util.cloneMessage(msg);\n    alarmControlMsg.event = {\n        type: \"ALARM_OFF\",\n        reason: \"system_disarmed\",\n        note: \"System disarmed by user\",\n        intrusionId: null,\n        evidence: [],\n        state: \"inactive\",\n        ts: now\n    };\n    alarmControlMsg.statusUpdate = {\n        armed: false,\n        state: \"inactive\",\n        intrusionId: null,\n        evidence: [],\n        ts: now\n    };\n} else {\n    flow.set(\"securityState\", \"active\");\n    flow.set(\"baseline\", { distanceCm: null, capturedAt: null });\n}\n\nconst mqttMsg = RED.util.cloneMessage(msg);\nmqttMsg.topic = \"vehicle/security/status\";\nmqttMsg.payload = {\n    armed,\n    state: flow.get(\"securityState\"),\n    baseline: flow.get(\"baseline\"),\n    ts: now\n};\n\nconst baselineMsg = RED.util.cloneMessage(msg);\nbaselineMsg.payload = {\n    armed,\n    captureBaseline: armed,\n    ts: now\n};\n\nmsg.payload = {\n    ok: true,\n    armed,\n    state: flow.get(\"securityState\"),\n    baseline: flow.get(\"baseline\"),\n    ts: now\n};\n\nreturn [msg, mqttMsg, baselineMsg, alarmControlMsg];",
        "outputs": 4,
        "timeout": 0,
        "noerr": 0,
        "initialize": "",
        "finalize": "",
        "libs": [],
        "x": 600,
        "y": 300,
        "wires": [
            [
                "511e97e419be5a46"
            ],
            [
                "5e1791bb4713a3ce"
            ],
            [
                "1e6ecf529f287354"
            ],
            [
                "1ca53671077d195c"
            ]
        ]
    },
    {
        "id": "511e97e419be5a46",
        "type": "http response",
        "z": "0e992f61a706eb58",
        "g": "75f65aa6282bdbfe",
        "name": "Arm Response",
        "statusCode": "",
        "headers": {},
        "x": 820,
        "y": 260,
        "wires": []
    },
    {
        "id": "5e1791bb4713a3ce",
        "type": "mqtt out",
        "z": "0e992f61a706eb58",
        "g": "5cc691194be3a9d8",
        "name": "Security Status MQTT Out",
        "topic": "",
        "qos": "1",
        "retain": "",
        "respTopic": "",
        "contentType": "",
        "userProps": "",
        "correl": "",
        "expiry": "",
        "broker": "mqtt_broker_pi1",
        "x": 1120,
        "y": 360,
        "wires": []
    },
    {
        "id": "1e6ecf529f287354",
        "type": "link out",
        "z": "0e992f61a706eb58",
        "g": "5cc691194be3a9d8",
        "name": "To Baseline Capture",
        "mode": "link",
        "links": [
            "046dc45923aa5596"
        ],
        "x": 1025,
        "y": 420,
        "wires": []
    },
    {
        "id": "2f017fb9807f908a",
        "type": "http in",
        "z": "0e992f61a706eb58",
        "g": "c493a96ad53dfc0d",
        "name": "GET /api/status",
        "url": "/api/status",
        "method": "get",
        "upload": false,
        "skipBodyParsing": false,
        "swaggerDoc": "",
        "x": 160,
        "y": 460,
        "wires": [
            [
                "ea91053b0fb8900e"
            ]
        ]
    },
    {
        "id": "ea91053b0fb8900e",
        "type": "function",
        "z": "0e992f61a706eb58",
        "g": "c493a96ad53dfc0d",
        "name": "Build Status Response",
        "func": "/**\n * Return current system status for the dashboard.\n */\nconst payload = {\n    armed: Boolean(flow.get(\"armed\")),\n    state: flow.get(\"securityState\") || \"inactive\",\n    settings: flow.get(\"settings\") || {},\n    baseline: flow.get(\"baseline\") || {},\n    last: flow.get(\"last\") || {},\n    intrusion: flow.get(\"intrusion\") || {},\n    alarm: flow.get(\"alarm\") || {},\n    ts: Date.now()\n};\n\nmsg.payload = payload;\nreturn msg;",
        "outputs": 1,
        "timeout": 0,
        "noerr": 0,
        "initialize": "",
        "finalize": "",
        "libs": [],
        "x": 380,
        "y": 460,
        "wires": [
            [
                "1f6857ce7e2b2c23"
            ]
        ]
    },
    {
        "id": "1f6857ce7e2b2c23",
        "type": "http response",
        "z": "0e992f61a706eb58",
        "g": "c493a96ad53dfc0d",
        "name": "Status Response",
        "statusCode": "",
        "headers": {},
        "x": 610,
        "y": 460,
        "wires": []
    },
    {
        "id": "463673ed19baf5d9",
        "type": "http in",
        "z": "0e992f61a706eb58",
        "g": "38d9086a2977fa73",
        "name": "POST /api/resolve",
        "url": "/api/resolve",
        "method": "post",
        "upload": false,
        "skipBodyParsing": false,
        "swaggerDoc": "",
        "x": 170,
        "y": 600,
        "wires": [
            [
                "f6fe70541e8bda69"
            ]
        ]
    },
    {
        "id": "f6fe70541e8bda69",
        "type": "json",
        "z": "0e992f61a706eb58",
        "g": "38d9086a2977fa73",
        "name": "Parse Resolve Request",
        "property": "payload",
        "action": "obj",
        "pretty": false,
        "x": 410,
        "y": 600,
        "wires": [
            [
                "ce0dd89034e3f85a"
            ]
        ]
    },
    {
        "id": "ce0dd89034e3f85a",
        "type": "function",
        "z": "0e992f61a706eb58",
        "g": "38d9086a2977fa73",
        "name": "Resolve Active Alarm",
        "func": "/**\n * Resolve an active suspicious/alarm incident from the dashboard.\n * Keeps the original HTTP msg so the http response node can reply correctly.\n */\nconst now = Date.now();\nconst body = msg.payload || {};\nconst armed = Boolean(flow.get(\"armed\"));\nconst intrusion = flow.get(\"intrusion\") || {};\n\nif (!armed) {\n    msg.statusCode = 400;\n    msg.payload = { ok: false, error: \"System is not armed\", ts: now };\n    return [msg, null, null, null];\n}\n\nif (!intrusion.id || intrusion.status !== \"open\") {\n    msg.statusCode = 409;\n    msg.payload = { ok: false, error: \"No active intrusion\", ts: now };\n    return [msg, null, null, null];\n}\n\nif (body.intrusionId && body.intrusionId !== intrusion.id) {\n    msg.statusCode = 409;\n    msg.payload = {\n        ok: false,\n        error: \"Intrusion ID mismatch\",\n        activeIntrusionId: intrusion.id,\n        requestedIntrusionId: body.intrusionId,\n        ts: now\n    };\n    return [msg, null, null, null];\n}\n\nintrusion.status = \"resolved\";\nintrusion.closedAt = now;\nintrusion.note = body.note || \"Resolved by user\";\n\nflow.set(\"intrusion\", intrusion);\nflow.set(\"securityState\", \"resolved\");\nflow.set(\"resolvedUntil\", now + 5000);\n\nconst eventMsg = RED.util.cloneMessage(msg);\neventMsg.event = {\n    type: \"ALARM_OFF\",\n    reason: body.resolutionType || \"user_resolved\",\n    note: intrusion.note,\n    intrusionId: intrusion.id,\n    evidence: intrusion.confirmedBy || [],\n    picturePath: intrusion.picturePath || \"\",\n    videoPath: intrusion.videoPath || \"\",\n    state: \"resolved\",\n    ts: now\n};\neventMsg.statusUpdate = {\n    armed: true,\n    state: \"resolved\",\n    intrusionId: intrusion.id,\n    evidence: intrusion.confirmedBy || [],\n    ts: now\n};\n\nconst mqttMsg = RED.util.cloneMessage(msg);\nmqttMsg.topic = \"vehicle/security/status\";\nmqttMsg.payload = eventMsg.statusUpdate;\n\nmsg.statusCode = 200;\nmsg.payload = {\n    ok: true,\n    message: \"Intrusion resolved\",\n    intrusionId: intrusion.id,\n    state: \"resolved\",\n    ts: now\n};\n\nreturn [msg, mqttMsg, eventMsg, eventMsg];",
        "outputs": 4,
        "timeout": 0,
        "noerr": 0,
        "initialize": "",
        "finalize": "",
        "libs": [],
        "x": 660,
        "y": 600,
        "wires": [
            [
                "0b351037472e36e4"
            ],
            [
                "5e1791bb4713a3ce"
            ],
            [
                "1ca53671077d195c"
            ],
            []
        ]
    },
    {
        "id": "0b351037472e36e4",
        "type": "http response",
        "z": "0e992f61a706eb58",
        "g": "38d9086a2977fa73",
        "name": "Resolve Response",
        "statusCode": "",
        "headers": {},
        "x": 890,
        "y": 580,
        "wires": []
    },
    {
        "id": "1ca53671077d195c",
        "type": "link out",
        "z": "0e992f61a706eb58",
        "g": "5cc691194be3a9d8",
        "name": "To Alarm Controller",
        "mode": "link",
        "links": [
            "03ad7b18a394a83b"
        ],
        "x": 1025,
        "y": 460,
        "wires": []
    },
    {
        "id": "aa85db266027c50e",
        "type": "link out",
        "z": "0e992f61a706eb58",
        "g": "5cc691194be3a9d8",
        "name": "To Event Persistence",
        "mode": "link",
        "links": [
            "9920a4a96963e478"
        ],
        "x": 1025,
        "y": 500,
        "wires": []
    },
    {
        "id": "8d5ceb9a904f3503",
        "type": "http in",
        "z": "0e992f61a706eb58",
        "g": "459424595753cf62",
        "name": "POST /api/trigger-alarm",
        "url": "/api/trigger-alarm",
        "method": "post",
        "upload": false,
        "skipBodyParsing": false,
        "swaggerDoc": "",
        "x": 180,
        "y": 760,
        "wires": [
            [
                "eb78f533eb9a17d3"
            ]
        ]
    },
    {
        "id": "eb78f533eb9a17d3",
        "type": "json",
        "z": "0e992f61a706eb58",
        "g": "459424595753cf62",
        "name": "Parse Trigger Alarm Request",
        "property": "payload",
        "action": "obj",
        "pretty": false,
        "x": 440,
        "y": 760,
        "wires": [
            [
                "b3ecbf97c400be84"
            ]
        ]
    },
    {
        "id": "b3ecbf97c400be84",
        "type": "function",
        "z": "0e992f61a706eb58",
        "g": "459424595753cf62",
        "name": "Force Alarm Escalation",
        "func": "/**\n * Escalate an existing suspicious intrusion to alarm.\n * Keeps the original HTTP msg so the http response node can reply correctly.\n */\nconst now = Date.now();\nconst body = msg.payload || {};\nconst armed = Boolean(flow.get(\"armed\"));\nconst intrusion = flow.get(\"intrusion\") || {};\nlet state = flow.get(\"securityState\") || \"inactive\";\n\nif (!armed) {\n    msg.statusCode = 400;\n    msg.payload = { ok: false, error: \"System is not armed\", ts: now };\n    return [msg, null, null, null];\n}\n\nif (!intrusion.id || intrusion.status !== \"open\") {\n    msg.statusCode = 409;\n    msg.payload = { ok: false, error: \"No active intrusion available\", ts: now };\n    return [msg, null, null, null];\n}\n\nif (body.intrusionId && body.intrusionId !== intrusion.id) {\n    msg.statusCode = 409;\n    msg.payload = {\n        ok: false,\n        error: \"Intrusion ID mismatch\",\n        activeIntrusionId: intrusion.id,\n        requestedIntrusionId: body.intrusionId,\n        ts: now\n    };\n    return [msg, null, null, null];\n}\n\nif (state !== \"suspicious\") {\n    msg.statusCode = 409;\n    msg.payload = {\n        ok: false,\n        error: `Cannot escalate from state ${state}`,\n        ts: now\n    };\n    return [msg, null, null, null];\n}\n\nstate = \"alarm\";\nintrusion.lastEvidenceAt = now;\nintrusion.confirmedBy = Array.from(\n    new Set([...(intrusion.confirmedBy || []), \"dashboard_confirmed\"])\n);\n\nflow.set(\"securityState\", state);\nflow.set(\"intrusion\", intrusion);\n\nconst eventMsg = RED.util.cloneMessage(msg);\neventMsg.event = {\n    type: \"ALARM_ON\",\n    reason: \"user_requested_alarm\",\n    triggerSource: body.triggerSource || \"dashboard_user_confirmation\",\n    note: body.note || \"Alarm requested by dashboard\",\n    intrusionId: intrusion.id,\n    evidence: intrusion.confirmedBy,\n    picturePath: intrusion.picturePath || \"\",\n    videoPath: intrusion.videoPath || \"\",\n    armed: true,\n    state: \"alarm\",\n    ts: now\n};\neventMsg.statusUpdate = {\n    armed: true,\n    state: \"alarm\",\n    intrusionId: intrusion.id,\n    evidence: intrusion.confirmedBy,\n    ts: now\n};\n\nconst mqttMsg = RED.util.cloneMessage(msg);\nmqttMsg.topic = \"vehicle/security/status\";\nmqttMsg.payload = eventMsg.statusUpdate;\n\nmsg.statusCode = 200;\nmsg.payload = {\n    ok: true,\n    message: \"Alarm triggered\",\n    intrusionId: intrusion.id,\n    state: \"alarm\",\n    ts: now\n};\n\nreturn [msg, mqttMsg, eventMsg, eventMsg];",
        "outputs": 4,
        "timeout": 0,
        "noerr": 0,
        "initialize": "",
        "finalize": "",
        "libs": [],
        "x": 710,
        "y": 760,
        "wires": [
            [
                "6f855d6da668d3ef"
            ],
            [
                "5e1791bb4713a3ce"
            ],
            [
                "1ca53671077d195c"
            ],
            []
        ]
    },
    {
        "id": "6f855d6da668d3ef",
        "type": "http response",
        "z": "0e992f61a706eb58",
        "g": "459424595753cf62",
        "name": "Trigger Alarm Response",
        "statusCode": "",
        "headers": {},
        "x": 970,
        "y": 740,
        "wires": []
    },
    {
        "id": "6207ffa8f84e5c6a",
        "type": "comment",
        "z": "0e992f61a706eb58",
        "g": "dfaa92d4dd849eab",
        "name": "Initialization",
        "info": "",
        "x": 170,
        "y": 120,
        "wires": []
    },
    {
        "id": "8d451422dd375d1d",
        "type": "comment",
        "z": "0e992f61a706eb58",
        "g": "75f65aa6282bdbfe",
        "name": "Arm/Disarm",
        "info": "",
        "x": 150,
        "y": 260,
        "wires": []
    },
    {
        "id": "3e7c290b44363b6b",
        "type": "json",
        "z": "0e992f61a706eb58",
        "g": "75f65aa6282bdbfe",
        "name": "Parse Arm Request",
        "property": "payload",
        "action": "obj",
        "pretty": false,
        "x": 370,
        "y": 300,
        "wires": [
            [
                "4bcc2a14d33814a7"
            ]
        ]
    },
    {
        "id": "dda0923130ab8939",
        "type": "comment",
        "z": "0e992f61a706eb58",
        "g": "c493a96ad53dfc0d",
        "name": "Status",
        "info": "",
        "x": 130,
        "y": 420,
        "wires": []
    },
    {
        "id": "e85567546df25f38",
        "type": "comment",
        "z": "0e992f61a706eb58",
        "g": "38d9086a2977fa73",
        "name": "Resolve",
        "info": "",
        "x": 140,
        "y": 560,
        "wires": []
    },
    {
        "id": "65f4a64fb60f38bc",
        "type": "comment",
        "z": "0e992f61a706eb58",
        "g": "459424595753cf62",
        "name": "Force Alarm",
        "info": "",
        "x": 150,
        "y": 720,
        "wires": []
    },
    {
        "id": "e16a31d51c76621e",
        "type": "comment",
        "z": "0e992f61a706eb58",
        "g": "5cc691194be3a9d8",
        "name": "PI1 - Core State & API",
        "info": "",
        "x": 160,
        "y": 60,
        "wires": []
    },
    {
        "id": "8692d60c3afac9ea",
        "type": "grovepi-dht11",
        "z": "0e992f61a706eb58",
        "g": "6229e595b7e29330",
        "name": "Climate Sensor",
        "interval": "5",
        "unit": "s",
        "pin": "7",
        "sensorname": "DHT11",
        "sensorid": "dht11.1",
        "x": 1440,
        "y": 160,
        "wires": [
            [
                "e0185a457c0f36cb"
            ]
        ]
    },
    {
        "id": "e0185a457c0f36cb",
        "type": "function",
        "z": "0e992f61a706eb58",
        "g": "6229e595b7e29330",
        "name": "Format Climate Reading",
        "func": "/**\n * Normalize DHT11 output and keep latest climate values in flow context.\n */\nconst now = Date.now();\nconst temperatureC = Number(msg.payload[0]);\nconst humidity = Number(msg.payload[1]);\n\nconst last = flow.get(\"last\") || {};\nlast.temperatureC = temperatureC;\nlast.humidity = humidity;\nlast.climateAt = now;\nflow.set(\"last\", last);\n\nnode.send([\n    {\n        payload: {\n            measurement: \"vehicle_climate\",\n            tags: {\n                device: \"pi1\",\n                sensor: \"dht11\"\n            },\n            fields: {\n                temperatureC,\n                humidity\n            },\n            timestamp: new Date(now)\n        }\n    },\n    {\n        payload: {\n            sensor: \"dht11\",\n            temperatureC,\n            humidity,\n            ts: now\n        }\n    }\n]);\n\nreturn null;",
        "outputs": 2,
        "timeout": 0,
        "noerr": 0,
        "initialize": "",
        "finalize": "",
        "libs": [],
        "x": 1670,
        "y": 160,
        "wires": [
            [
                "be6b498ae29ffb92"
            ],
            [
                "500ce2f7ea2429e1"
            ]
        ]
    },
    {
        "id": "aa04da7c9300617c",
        "type": "comment",
        "z": "0e992f61a706eb58",
        "g": "73bca6c267ce7e72",
        "name": "PI1 - Local Sensors",
        "info": "",
        "x": 1430,
        "y": 60,
        "wires": []
    },
    {
        "id": "be6b498ae29ffb92",
        "type": "influxdb out",
        "z": "0e992f61a706eb58",
        "g": "6229e595b7e29330",
        "influxdb": "",
        "name": "Climate Metrics Out",
        "measurement": "vehicle_climate",
        "precision": "",
        "retentionPolicy": "",
        "database": "database",
        "precisionV18FluxV20": "ms",
        "retentionPolicyV18Flux": "",
        "org": "organisation",
        "bucket": "bucket",
        "x": 1910,
        "y": 140,
        "wires": []
    },
    {
        "id": "500ce2f7ea2429e1",
        "type": "link out",
        "z": "0e992f61a706eb58",
        "g": "6229e595b7e29330",
        "name": "To Dashboard Metrics",
        "mode": "link",
        "links": [],
        "x": 1835,
        "y": 180,
        "wires": []
    },
    {
        "id": "03a7735eb8d49cc1",
        "type": "grovepi-ultrasonic",
        "z": "0e992f61a706eb58",
        "g": "0608b5f4d7a72b5a",
        "name": "Driver Seat Range Sensor",
        "mode": "timer",
        "interval": 1,
        "unit": "s",
        "pin": "5",
        "sensorname": "Ultrasonic Ranger",
        "sensorid": "grovepi.ultrasonic-ranger.1",
        "x": 1470,
        "y": 320,
        "wires": [
            [
                "abd2ccc7d536c490"
            ]
        ]
    },
    {
        "id": "abd2ccc7d536c490",
        "type": "function",
        "z": "0e992f61a706eb58",
        "g": "0608b5f4d7a72b5a",
        "name": "Normalize Distance Reading",
        "func": "/**\n * Normalize ultrasonic readings and store the latest distance reading.\n */\nconst now = Date.now();\nconst distanceCm = typeof msg.payload === \"number\"\n    ? Number(msg.payload)\n    : Number(msg.payload?.distance ?? msg.payload?.cm);\n\nconst last = flow.get(\"last\") || {};\nlast.distanceCm = distanceCm;\nlast.distanceAt = now;\nflow.set(\"last\", last);\n\nmsg.payload = {\n    sensor: \"ultrasonic\",\n    distanceCm,\n    ts: now\n};\n\nreturn msg;",
        "outputs": 1,
        "timeout": 0,
        "noerr": 0,
        "initialize": "",
        "finalize": "",
        "libs": [],
        "x": 1740,
        "y": 320,
        "wires": [
            [
                "bf5c2108be768111"
            ]
        ]
    },
    {
        "id": "bf5c2108be768111",
        "type": "link out",
        "z": "0e992f61a706eb58",
        "g": "0608b5f4d7a72b5a",
        "name": "To Detection Engine",
        "mode": "link",
        "links": [
            "ced47629dad00272"
        ],
        "x": 1915,
        "y": 320,
        "wires": []
    },
    {
        "id": "046dc45923aa5596",
        "type": "link in",
        "z": "0e992f61a706eb58",
        "g": "be9c8d8a9e47d8d2",
        "name": "From Baseline Capture",
        "links": [
            "1e6ecf529f287354"
        ],
        "x": 1375,
        "y": 460,
        "wires": [
            [
                "72306b47b1bb7e82"
            ]
        ]
    },
    {
        "id": "72306b47b1bb7e82",
        "type": "function",
        "z": "0e992f61a706eb58",
        "g": "be9c8d8a9e47d8d2",
        "name": "Capture Distance Baseline",
        "func": "/**\n * When the system is armed, capture the current distance as the driver-seat baseline.\n */\nconst now = Date.now();\nconst request = msg.payload || {};\nconst armed = Boolean(flow.get(\"armed\"));\nconst last = flow.get(\"last\") || {};\n\nif (!armed || !request.captureBaseline) {\n    return null;\n}\n\nif (last.distanceCm === null || last.distanceCm === undefined || Number.isNaN(last.distanceCm)) {\n    node.status({\n        fill: \"yellow\",\n        shape: \"ring\",\n        text: \"waiting for distance reading\"\n    });\n    return null;\n}\n\nconst baseline = {\n    distanceCm: Number(last.distanceCm),\n    capturedAt: now\n};\n\nflow.set(\"baseline\", baseline);\nflow.set(\"securityState\", \"active\");\n\nmsg.topic = \"vehicle/security/status\";\nmsg.payload = {\n    armed: true,\n    state: \"active\",\n    baseline,\n    ts: now\n};\n\nnode.status({\n    fill: \"green\",\n    shape: \"dot\",\n    text: `baseline ${baseline.distanceCm}cm`\n});\n\nreturn msg;",
        "outputs": 1,
        "timeout": 0,
        "noerr": 0,
        "initialize": "",
        "finalize": "",
        "libs": [],
        "x": 1560,
        "y": 460,
        "wires": [
            [
                "aea31bc84326236c"
            ]
        ]
    },
    {
        "id": "aea31bc84326236c",
        "type": "mqtt out",
        "z": "0e992f61a706eb58",
        "g": "be9c8d8a9e47d8d2",
        "name": "Baseline Status MQTT Out",
        "topic": "",
        "qos": "1",
        "retain": "",
        "respTopic": "",
        "contentType": "",
        "userProps": "",
        "correl": "",
        "expiry": "",
        "broker": "mqtt_broker_pi1",
        "x": 1840,
        "y": 460,
        "wires": []
    },
    {
        "id": "d1221e354410fc66",
        "type": "comment",
        "z": "0e992f61a706eb58",
        "g": "6229e595b7e29330",
        "name": "Climate",
        "info": "",
        "x": 1410,
        "y": 120,
        "wires": []
    },
    {
        "id": "6071d58d4a545640",
        "type": "comment",
        "z": "0e992f61a706eb58",
        "g": "0608b5f4d7a72b5a",
        "name": "Distance",
        "info": "",
        "x": 1420,
        "y": 280,
        "wires": []
    },
    {
        "id": "672abb38db405708",
        "type": "comment",
        "z": "0e992f61a706eb58",
        "g": "be9c8d8a9e47d8d2",
        "name": "Baseline Capture",
        "info": "",
        "x": 1440,
        "y": 420,
        "wires": []
    },
    {
        "id": "c49bc9415318b8c4",
        "type": "comment",
        "z": "0e992f61a706eb58",
        "g": "c07101037867795b",
        "name": "PI1 - Pi2 Intake & Detection",
        "info": "",
        "x": 1460,
        "y": 580,
        "wires": []
    },
    {
        "id": "5921bbfc575a0b88",
        "type": "mqtt in",
        "z": "0e992f61a706eb58",
        "g": "93149a58644b3b8a",
        "name": "Pi2 Sensor Bundle In",
        "topic": "vehicle/pi2/sensors",
        "qos": "1",
        "datatype": "auto-detect",
        "broker": "mqtt_broker_pi1",
        "nl": false,
        "rap": true,
        "rh": 0,
        "inputs": 0,
        "x": 1460,
        "y": 680,
        "wires": [
            [
                "2c91b78b561f1c10"
            ]
        ]
    },
    {
        "id": "2c91b78b561f1c10",
        "type": "json",
        "z": "0e992f61a706eb58",
        "g": "93149a58644b3b8a",
        "name": "Parse Pi2 Payload",
        "property": "payload",
        "action": "obj",
        "pretty": false,
        "x": 1690,
        "y": 680,
        "wires": [
            [
                "c2c555de1b5b0a6c"
            ]
        ]
    },
    {
        "id": "c2c555de1b5b0a6c",
        "type": "function",
        "z": "0e992f61a706eb58",
        "g": "93149a58644b3b8a",
        "name": "Normalize Pi2 Sensor Bundle",
        "func": "/**\n * Normalize the Pi 2 sensor bundle and update latest cached readings.\n */\nconst now = Date.now();\nconst p = msg.payload || {};\nconst last = flow.get(\"last\") || {};\n\nif (p.vibration !== undefined) {\n    last.vibration = Number(p.vibration);\n    last.vibrationAt = p.ts || now;\n}\n\nif (p.accel) {\n    const x = Number(p.accel.x || 0);\n    const y = Number(p.accel.y || 0);\n    const z = Number(p.accel.z || 0);\n    last.accelMag = Math.sqrt((x * x) + (y * y) + (z * z));\n    last.accelAt = p.ts || now;\n}\n\nflow.set(\"last\", last);\n\nmsg.payload = {\n    sensor: \"pi2_bundle\",\n    vibration: last.vibration,\n    accelMag: last.accelMag,\n    ts: p.ts || now\n};\n\nreturn msg;",
        "outputs": 1,
        "timeout": 0,
        "noerr": 0,
        "initialize": "",
        "finalize": "",
        "libs": [],
        "x": 1940,
        "y": 680,
        "wires": [
            [
                "45716de8bb60743b"
            ]
        ]
    },
    {
        "id": "ced47629dad00272",
        "type": "link in",
        "z": "0e992f61a706eb58",
        "g": "b504de31678f72cd",
        "name": "Ultrasonic Reading In",
        "links": [
            "bf5c2108be768111"
        ],
        "x": 1375,
        "y": 820,
        "wires": [
            [
                "45716de8bb60743b"
            ]
        ]
    },
    {
        "id": "45716de8bb60743b",
        "type": "function",
        "z": "0e992f61a706eb58",
        "g": "93149a58644b3b8a",
        "name": "Security Detection Engine",
        "func": "/**\n * Unified detection engine for GrovePi 1 and Pi 2 readings.\n * Low-level sensor:\n * - ultrasonic -> suspicious\n *\n * High-level sensors:\n * - vibration\n * - accelerometer magnitude\n *\n * High-level evidence can trigger alarm without seat occupancy.\n */\nconst now = Date.now();\nconst armed = Boolean(flow.get(\"armed\"));\nlet state = flow.get(\"securityState\") || \"inactive\";\nconst settings = flow.get(\"settings\") || {};\nconst baseline = flow.get(\"baseline\") || {};\nconst last = flow.get(\"last\") || {};\nlet intrusion = flow.get(\"intrusion\") || {};\nconst resolvedUntil = flow.get(\"resolvedUntil\");\n\nif (!armed) {\n    return null;\n}\n\n/**\n * Return resolved mode back to active after the short display window.\n */\nif (state === \"resolved\" && resolvedUntil && now >= resolvedUntil) {\n    flow.set(\"securityState\", \"active\");\n    flow.set(\"resolvedUntil\", null);\n\n    const currentIntrusion = flow.get(\"intrusion\") || {};\n    if (currentIntrusion.status === \"resolved\" || currentIntrusion.status === \"timed_out\") {\n        flow.set(\"intrusion\", {\n            id: null,\n            startedAt: null,\n            lastEvidenceAt: null,\n            confirmedBy: [],\n            status: \"closed\",\n            picturePath: null,\n            videoPath: null,\n            videoActive: false,\n            note: null,\n            closedAt: currentIntrusion.closedAt || now\n        });\n    }\n\n    state = \"active\";\n}\n\n/**\n * Wait until baseline exists before evaluating occupancy.\n */\nif (baseline.distanceCm === null || baseline.distanceCm === undefined) {\n    return null;\n}\n\nconst recent = (timestamp, maxMs) => Boolean(timestamp) && ((now - timestamp) <= maxMs);\n\nconst seatDelta = Math.abs((last.distanceCm ?? baseline.distanceCm) - baseline.distanceCm);\nconst seatTriggered = seatDelta >= settings.seatDeltaCm;\n\nlet seatStableSince = flow.get(\"seatStableSince\") || null;\nif (seatTriggered) {\n    if (!seatStableSince) {\n        seatStableSince = now;\n        flow.set(\"seatStableSince\", seatStableSince);\n    }\n} else {\n    flow.set(\"seatStableSince\", null);\n    seatStableSince = null;\n}\n\nconst seatDebounced = Boolean(seatStableSince) && ((now - seatStableSince) >= settings.seatDebounceMs);\n\nconst vibrationTriggered =\n    Number(last.vibration || 0) >= settings.vibrationSpike &&\n    recent(last.vibrationAt, settings.confirmWindowMs);\n\nconst accelTriggered =\n    Number(last.accelMag || 0) >= settings.accelMagSpike &&\n    recent(last.accelAt, settings.confirmWindowMs);\n\nconst lowEvidence = [];\nconst highEvidence = [];\n\nif (seatDebounced) lowEvidence.push(\"ultrasonic\");\nif (vibrationTriggered) highEvidence.push(\"vibration\");\nif (accelTriggered) highEvidence.push(\"accel\");\n\nconst allEvidence = [...lowEvidence, ...highEvidence];\nconst suspiciousModeEnabled = Boolean(settings.suspiciousModeEnabled);\n\nconst ensureOpenIntrusion = () => {\n    if (!intrusion.id || intrusion.status !== \"open\") {\n        intrusion = {\n            id: `intr_${now}`,\n            startedAt: now,\n            lastEvidenceAt: now,\n            confirmedBy: [],\n            status: \"open\",\n            picturePath: null,\n            videoPath: null,\n            note: null,\n            closedAt: null\n        };\n    } else {\n        intrusion.lastEvidenceAt = now;\n    }\n};\n\nlet event = null;\nlet nextState = state;\n\n/**\n * ACTIVE -> SUSPICIOUS or ALARM\n */\nif (state === \"active\") {\n    const shouldAlarmImmediately =\n        highEvidence.length >= 1 || (lowEvidence.length >= 1 && highEvidence.length >= 1);\n\n    if (shouldAlarmImmediately || (!suspiciousModeEnabled && lowEvidence.length >= 1)) {\n        ensureOpenIntrusion();\n        intrusion.confirmedBy = Array.from(new Set([...(intrusion.confirmedBy || []), ...allEvidence]));\n        nextState = \"alarm\";\n        event = {\n            type: \"ALARM_ON\",\n            reason: shouldAlarmImmediately ? \"high_level_sensor\" : \"suspicious_mode_disabled\",\n            intrusionId: intrusion.id,\n            evidence: intrusion.confirmedBy,\n            state: nextState,\n            ts: now\n        };\n    } else if (lowEvidence.length >= 1 && suspiciousModeEnabled) {\n        ensureOpenIntrusion();\n        intrusion.confirmedBy = Array.from(new Set([...(intrusion.confirmedBy || []), ...lowEvidence]));\n        nextState = \"suspicious\";\n        event = {\n            type: \"INFO_SUSPICIOUS\",\n            reason: \"seat_delta\",\n            intrusionId: intrusion.id,\n            evidence: intrusion.confirmedBy,\n            state: nextState,\n            ts: now\n        };\n    }\n}\n\n/**\n * SUSPICIOUS -> ALARM or timeout back to ACTIVE\n */\nelse if (state === \"suspicious\") {\n    ensureOpenIntrusion();\n\n    if (highEvidence.length >= 1) {\n        intrusion.confirmedBy = Array.from(new Set([...(intrusion.confirmedBy || []), ...allEvidence]));\n        nextState = \"alarm\";\n        event = {\n            type: \"ALARM_ON\",\n            reason: \"confirmed_after_suspicious\",\n            intrusionId: intrusion.id,\n            evidence: intrusion.confirmedBy,\n            state: nextState,\n            ts: now\n        };\n    } else if ((now - intrusion.startedAt) >= settings.suspiciousTimeoutMs) {\n        intrusion.status = \"timed_out\";\n        intrusion.closedAt = now;\n        nextState = \"active\";\n        event = {\n            type: \"ALARM_OFF\",\n            reason: \"suspicious_timeout\",\n            intrusionId: intrusion.id,\n            evidence: intrusion.confirmedBy || [],\n            picturePath: intrusion.picturePath || \"\",\n            videoPath: intrusion.videoPath || \"\",\n            state: nextState,\n            ts: now\n        };\n    }\n}\n\n/**\n * Ignore detection while already in alarm.\n */\nelse if (state === \"alarm\") {\n    if (intrusion.id && intrusion.status === \"open\") {\n        intrusion.lastEvidenceAt = now;\n        intrusion.confirmedBy = Array.from(new Set([...(intrusion.confirmedBy || []), ...allEvidence]));\n        flow.set(\"intrusion\", intrusion);\n    }\n    return null;\n}\n\nif (!event) {\n    return null;\n}\n\nflow.set(\"securityState\", nextState);\n\nif (event.type === \"ALARM_OFF\" && event.reason === \"suspicious_timeout\") {\n    flow.set(\"intrusion\", intrusion);\n} else {\n    flow.set(\"intrusion\", intrusion);\n}\n\nreturn {\n    event,\n    statusUpdate: {\n        armed: true,\n        state: nextState,\n        intrusionId: event.intrusionId || intrusion.id || null,\n        evidence: intrusion.confirmedBy || [],\n        ts: now\n    }\n};",
        "outputs": 1,
        "timeout": 0,
        "noerr": 0,
        "initialize": "",
        "finalize": "",
        "libs": [],
        "x": 2210,
        "y": 680,
        "wires": [
            [
                "e339ee3e7f926e14"
            ]
        ]
    },
    {
        "id": "e339ee3e7f926e14",
        "type": "switch",
        "z": "0e992f61a706eb58",
        "g": "aad72eeb907091b5",
        "name": "Route Detection Event",
        "property": "event.type",
        "propertyType": "msg",
        "rules": [
            {
                "t": "eq",
                "v": "INFO_SUSPICIOUS",
                "vt": "str"
            },
            {
                "t": "eq",
                "v": "ALARM_ON",
                "vt": "str"
            },
            {
                "t": "eq",
                "v": "ALARM_OFF",
                "vt": "str"
            }
        ],
        "checkall": "true",
        "repair": false,
        "outputs": 3,
        "x": 1700,
        "y": 880,
        "wires": [
            [
                "be754b1a8f482a59",
                "fe92c5eaa6430a56",
                "f3b5737469a0ae23"
            ],
            [
                "c94b4efcf259fe8d",
                "be754b1a8f482a59",
                "fe92c5eaa6430a56",
                "f3b5737469a0ae23"
            ],
            [
                "be754b1a8f482a59",
                "fe92c5eaa6430a56",
                "1ba6a00a59d90dd3",
                "e56f211f1a234d45",
                "f3b5737469a0ae23"
            ]
        ]
    },
    {
        "id": "87c6979873121a16",
        "type": "mqtt out",
        "z": "0e992f61a706eb58",
        "g": "aad72eeb907091b5",
        "name": "Security Alert MQTT Out",
        "topic": "vehicle/security/alerts",
        "qos": "1",
        "retain": "",
        "respTopic": "",
        "contentType": "",
        "userProps": "",
        "correl": "",
        "expiry": "",
        "broker": "mqtt_broker_pi1",
        "x": 2410,
        "y": 820,
        "wires": []
    },
    {
        "id": "166ec84d0479edca",
        "type": "mqtt out",
        "z": "0e992f61a706eb58",
        "g": "aad72eeb907091b5",
        "name": "Security Status MQTT Out",
        "topic": "vehicle/security/status",
        "qos": "1",
        "retain": "",
        "respTopic": "",
        "contentType": "",
        "userProps": "",
        "correl": "",
        "expiry": "",
        "broker": "mqtt_broker_pi1",
        "x": 2420,
        "y": 880,
        "wires": []
    },
    {
        "id": "c94b4efcf259fe8d",
        "type": "link out",
        "z": "0e992f61a706eb58",
        "g": "aad72eeb907091b5",
        "name": "To Alarm Controller",
        "mode": "link",
        "links": [
            "03ad7b18a394a83b"
        ],
        "x": 1955,
        "y": 860,
        "wires": []
    },
    {
        "id": "7570e2d0c0bc7666",
        "type": "link out",
        "z": "0e992f61a706eb58",
        "g": "6d15c9fd9f5b6e7e",
        "name": "To Event Persistence",
        "mode": "link",
        "links": [
            "9920a4a96963e478"
        ],
        "x": 895,
        "y": 1380,
        "wires": []
    },
    {
        "id": "1ba6a00a59d90dd3",
        "type": "link out",
        "z": "0e992f61a706eb58",
        "g": "aad72eeb907091b5",
        "name": "To Dashboard Live Feed",
        "mode": "link",
        "links": [
            "4fa12711f176e1bb"
        ],
        "x": 1955,
        "y": 900,
        "wires": []
    },
    {
        "id": "9c0cfaf36b5bffab",
        "type": "comment",
        "z": "0e992f61a706eb58",
        "g": "93149a58644b3b8a",
        "name": "Pi 2 Intake",
        "info": "",
        "x": 1420,
        "y": 640,
        "wires": []
    },
    {
        "id": "98eba2328ce0078a",
        "type": "comment",
        "z": "0e992f61a706eb58",
        "g": "b504de31678f72cd",
        "name": "Ultrasonic Intake",
        "info": "",
        "x": 1440,
        "y": 780,
        "wires": []
    },
    {
        "id": "d937a38c42b348c3",
        "type": "comment",
        "z": "0e992f61a706eb58",
        "g": "aad72eeb907091b5",
        "name": "Detection Routing",
        "info": "",
        "x": 1690,
        "y": 820,
        "wires": []
    },
    {
        "id": "3815a81333d53168",
        "type": "comment",
        "z": "0e992f61a706eb58",
        "g": "ef1e886f28df8d51",
        "name": "PI1 - Alarm, Camera & Persistence",
        "info": "",
        "x": 200,
        "y": 1060,
        "wires": []
    },
    {
        "id": "03ad7b18a394a83b",
        "type": "link in",
        "z": "0e992f61a706eb58",
        "g": "71c8aa3b6b346885",
        "name": "Alarm Control In",
        "links": [
            "1ca53671077d195c",
            "c94b4efcf259fe8d"
        ],
        "x": 95,
        "y": 1160,
        "wires": [
            [
                "dc73d130ee96e626"
            ]
        ]
    },
    {
        "id": "dc73d130ee96e626",
        "type": "switch",
        "z": "0e992f61a706eb58",
        "g": "71c8aa3b6b346885",
        "name": "Alarm On Or Off",
        "property": "event.type",
        "propertyType": "msg",
        "rules": [
            {
                "t": "eq",
                "v": "ALARM_ON",
                "vt": "str"
            },
            {
                "t": "eq",
                "v": "ALARM_OFF",
                "vt": "str"
            }
        ],
        "checkall": "true",
        "repair": false,
        "outputs": 2,
        "x": 240,
        "y": 1160,
        "wires": [
            [
                "f5dc23973c30ac07",
                "a2e2b9722d48755b"
            ],
            [
                "8a85e827a930f392",
                "a2e2b9722d48755b"
            ]
        ]
    },
    {
        "id": "f5dc23973c30ac07",
        "type": "function",
        "z": "0e992f61a706eb58",
        "g": "71c8aa3b6b346885",
        "name": "Start Alarm State",
        "func": "/**\n * Start local alarm flashing/buzzing cycle.\n */\nflow.set(\"alarm\", {\n    active: true,\n    tickCount: 0,\n    ledState: 0\n});\n\nreturn msg;",
        "outputs": 1,
        "timeout": 0,
        "noerr": 0,
        "initialize": "",
        "finalize": "",
        "libs": [],
        "x": 450,
        "y": 1120,
        "wires": [
            [
                "8900cf9202efbd7a"
            ]
        ]
    },
    {
        "id": "8a85e827a930f392",
        "type": "function",
        "z": "0e992f61a706eb58",
        "g": "71c8aa3b6b346885",
        "name": "Stop Alarm State",
        "func": "/**\n * Stop local alarm devices and reset state.\n */\nflow.set(\"alarm\", {\n    active: false,\n    tickCount: 0,\n    ledState: 0\n});\n\nreturn [\n    { payload: 0 },\n    { payload: 0 },\n    { reset: true }\n];",
        "outputs": 3,
        "timeout": 0,
        "noerr": 0,
        "initialize": "",
        "finalize": "",
        "libs": [],
        "x": 450,
        "y": 1200,
        "wires": [
            [
                "faa613d260876a51"
            ],
            [
                "73598425fff63a7b"
            ],
            [
                "8900cf9202efbd7a"
            ]
        ]
    },
    {
        "id": "8900cf9202efbd7a",
        "type": "trigger",
        "z": "0e992f61a706eb58",
        "g": "c3bc344f2852449d",
        "name": "Alarm Tick",
        "op1": "1",
        "op2": "0",
        "op1type": "num",
        "op2type": "str",
        "duration": "-0.5",
        "extend": false,
        "overrideDelay": false,
        "units": "s",
        "reset": "reset",
        "bytopic": "all",
        "topic": "topic",
        "outputs": 1,
        "x": 690,
        "y": 1160,
        "wires": [
            [
                "f9d162e9615d1636"
            ]
        ]
    },
    {
        "id": "f9d162e9615d1636",
        "type": "function",
        "z": "0e992f61a706eb58",
        "g": "c3bc344f2852449d",
        "name": "Alarm Tick Router",
        "func": "/**\n * Alternate LED state and pulse buzzer while the alarm is active.\n */\nconst alarm = flow.get(\"alarm\") || { active: false, tickCount: 0, ledState: 0 };\n\nif (!alarm.active) {\n    return [null, null];\n}\n\nalarm.tickCount += 1;\nalarm.ledState = alarm.ledState ? 0 : 1;\nflow.set(\"alarm\", alarm);\n\nreturn [\n    { payload: 1 },\n    { payload: alarm.ledState }\n];",
        "outputs": 2,
        "timeout": 0,
        "noerr": 0,
        "initialize": "",
        "finalize": "",
        "libs": [],
        "x": 890,
        "y": 1160,
        "wires": [
            [
                "faa613d260876a51"
            ],
            [
                "73598425fff63a7b"
            ]
        ]
    },
    {
        "id": "faa613d260876a51",
        "type": "grovepi-buzzer",
        "z": "0e992f61a706eb58",
        "g": "c3bc344f2852449d",
        "name": "Alarm Buzzer",
        "pin": "3",
        "x": 1100,
        "y": 1120,
        "wires": []
    },
    {
        "id": "73598425fff63a7b",
        "type": "grovepi-led",
        "z": "0e992f61a706eb58",
        "g": "c3bc344f2852449d",
        "name": "Alarm LED",
        "pin": "4",
        "x": 1090,
        "y": 1200,
        "wires": []
    },
    {
        "id": "a2e2b9722d48755b",
        "type": "function",
        "z": "0e992f61a706eb58",
        "g": "6d15c9fd9f5b6e7e",
        "name": "Build Camera Commands",
        "func": "/**\n * Camera policy:\n * - INFO_SUSPICIOUS: capture a still image only\n * - ALARM_ON: start video recording as .h264\n * - ALARM_OFF: stop recording and convert .h264 -> .mp4\n *\n * Outputs:\n * 1 = Exec node\n * 2 = Dashboard live feed\n * 3 = Event persistence\n */\nconst event = msg.event || {};\nconst baseDir = \"/home/pi/autoguard\";\nconst scriptPath = `${baseDir}/camera_service.py`;\n\nlet intrusion = flow.get(\"intrusion\") || {\n    id: null,\n    startedAt: null,\n    lastEvidenceAt: null,\n    confirmedBy: [],\n    status: \"closed\",\n    picturePath: null,\n    videoPath: null,\n    videoActive: false,\n    note: null,\n    closedAt: null\n};\n\nconst activeIntrusionId = event.intrusionId || intrusion.id || null;\n\nconst imagePath = activeIntrusionId ? `${baseDir}/images/${activeIntrusionId}.jpg` : (intrusion.picturePath || \"\");\nconst h264Path = activeIntrusionId ? `${baseDir}/videos/${activeIntrusionId}.h264` : \"\";\nconst mp4Path = activeIntrusionId ? `${baseDir}/videos/${activeIntrusionId}.mp4` : (intrusion.videoPath || \"\");\nconst pidPath = activeIntrusionId ? `${baseDir}/videos/${activeIntrusionId}.pid` : \"\";\nconst logPath = activeIntrusionId\n    ? `/tmp/autoguard_camera_${activeIntrusionId}.log`\n    : `/tmp/autoguard_camera_generic.log`;\n\nconst liveFeedMsg = RED.util.cloneMessage(msg);\nconst persistenceMsg = RED.util.cloneMessage(msg);\nlet execMsg = null;\n\n// Suspicious -> capture picture only\nif (event.type === \"INFO_SUSPICIOUS\") {\n    if (!activeIntrusionId) {\n        return [null, null, null];\n    }\n\n    intrusion.id = intrusion.id || activeIntrusionId;\n    intrusion.picturePath = intrusion.picturePath || imagePath;\n    intrusion.videoPath = intrusion.videoPath || mp4Path;\n    intrusion.videoActive = false;\n    flow.set(\"intrusion\", intrusion);\n\n    liveFeedMsg.event.picturePath = intrusion.picturePath;\n    liveFeedMsg.event.videoPath = intrusion.videoPath || \"\";\n\n    persistenceMsg.event.picturePath = intrusion.picturePath;\n    persistenceMsg.event.videoPath = intrusion.videoPath || \"\";\n\n    execMsg = RED.util.cloneMessage(msg);\n    execMsg.payload = `-lc \"python3 ${scriptPath} capture-image --output '${intrusion.picturePath}' >'${logPath}' 2>&1\"`;\n\n    return [execMsg, liveFeedMsg, persistenceMsg];\n}\n\n// Alarm -> start video recording as h264\nif (event.type === \"ALARM_ON\") {\n    if (!activeIntrusionId) {\n        return [null, null, null];\n    }\n\n    intrusion.id = intrusion.id || activeIntrusionId;\n    intrusion.picturePath = intrusion.picturePath || imagePath;\n    intrusion.videoPath = intrusion.videoPath || mp4Path;\n    intrusion.videoActive = true;\n    flow.set(\"intrusion\", intrusion);\n\n    liveFeedMsg.event.picturePath = intrusion.picturePath;\n    liveFeedMsg.event.videoPath = intrusion.videoPath;\n\n    persistenceMsg.event.picturePath = intrusion.picturePath;\n    persistenceMsg.event.videoPath = intrusion.videoPath;\n\n    execMsg = RED.util.cloneMessage(msg);\n    execMsg.payload = `-lc \"python3 ${scriptPath} start-video --output '${h264Path}' --pid-file '${pidPath}' >'${logPath}' 2>&1 &\"`;\n\n    return [execMsg, liveFeedMsg, persistenceMsg];\n}\n\n// Resolve / timeout / disarm -> stop video and convert to mp4\nif (event.type === \"ALARM_OFF\") {\n    liveFeedMsg.event.picturePath = intrusion.picturePath || \"\";\n    liveFeedMsg.event.videoPath = intrusion.videoPath || \"\";\n\n    persistenceMsg.event.picturePath = intrusion.picturePath || \"\";\n    persistenceMsg.event.videoPath = intrusion.videoPath || \"\";\n\n    if (!intrusion.videoActive || !activeIntrusionId) {\n        return [null, liveFeedMsg, persistenceMsg];\n    }\n\n    const stopH264Path = `${baseDir}/videos/${activeIntrusionId}.h264`;\n    const stopMp4Path = `${baseDir}/videos/${activeIntrusionId}.mp4`;\n    const stopPidPath = `${baseDir}/videos/${activeIntrusionId}.pid`;\n\n    intrusion.videoActive = false;\n    intrusion.videoPath = stopMp4Path;\n    flow.set(\"intrusion\", intrusion);\n\n    execMsg = RED.util.cloneMessage(msg);\n    execMsg.payload = `-lc \"python3 ${scriptPath} stop-video --pid-file '${stopPidPath}' --h264-input '${stopH264Path}' --mp4-output '${stopMp4Path}' >'${logPath}' 2>&1\"`;\n\n    return [execMsg, liveFeedMsg, persistenceMsg];\n}\n\nreturn [null, null, null];",
        "outputs": 3,
        "timeout": 0,
        "noerr": 0,
        "initialize": "",
        "finalize": "",
        "libs": [],
        "x": 790,
        "y": 1340,
        "wires": [
            [
                "fe886807dd77d494",
                "ad1c7710ab01be2b"
            ],
            [
                "25c59be20820f116"
            ],
            [
                "7570e2d0c0bc7666"
            ]
        ]
    },
    {
        "id": "fe886807dd77d494",
        "type": "exec",
        "z": "0e992f61a706eb58",
        "g": "6d15c9fd9f5b6e7e",
        "command": "bash",
        "addpay": "payload",
        "append": "",
        "useSpawn": "false",
        "timer": "",
        "winHide": false,
        "oldrc": false,
        "name": "Camera Command",
        "x": 1030,
        "y": 1340,
        "wires": [
            [
                "0ee56e928c0e6155"
            ],
            [
                "0ee56e928c0e6155"
            ],
            [
                "0ee56e928c0e6155"
            ]
        ]
    },
    {
        "id": "9920a4a96963e478",
        "type": "link in",
        "z": "0e992f61a706eb58",
        "g": "7404463c72010353",
        "name": "Persistence In",
        "links": [
            "aa85db266027c50e",
            "7570e2d0c0bc7666",
            "e56f211f1a234d45"
        ],
        "x": 95,
        "y": 1340,
        "wires": [
            [
                "9932d1a9eb8e9e30"
            ]
        ]
    },
    {
        "id": "9932d1a9eb8e9e30",
        "type": "function",
        "z": "0e992f61a706eb58",
        "g": "7404463c72010353",
        "name": "Build Security Event Point",
        "func": "/**\n * Save security events with sensor snapshot context.\n * Falls back to the current intrusion record for media paths.\n */\nconst event = msg.event || {};\nconst last = flow.get(\"last\") || {};\nconst baseline = flow.get(\"baseline\") || {};\nconst intrusion = flow.get(\"intrusion\") || {};\n\nconst picturePath = event.picturePath || intrusion.picturePath || \"\";\nconst videoPath = event.videoPath || intrusion.videoPath || \"\";\n\nmsg.payload = {\n    measurement: \"security_events\",\n    tags: {\n        device: \"pi1\",\n        intrusionId: event.intrusionId || \"none\",\n        type: event.type || \"unknown\"\n    },\n    fields: {\n        state: String(event.state || flow.get(\"securityState\") || \"unknown\"),\n        reason: String(event.reason || \"\"),\n        evidence: JSON.stringify(event.evidence || []),\n        picture_path: String(picturePath),\n        video_path: String(videoPath),\n        distance_cm: last.distanceCm ?? null,\n        baseline_cm: baseline.distanceCm ?? null,\n        vibration: last.vibration ?? null,\n        accel_mag: last.accelMag ?? null\n    },\n    timestamp: new Date(event.ts || Date.now())\n};\n\nreturn msg;",
        "outputs": 1,
        "timeout": 0,
        "noerr": 0,
        "initialize": "",
        "finalize": "",
        "libs": [],
        "x": 270,
        "y": 1340,
        "wires": [
            [
                "b5f96ecabad2153e"
            ]
        ]
    },
    {
        "id": "b5f96ecabad2153e",
        "type": "influxdb out",
        "z": "0e992f61a706eb58",
        "g": "7404463c72010353",
        "influxdb": "",
        "name": "Security Event Out",
        "measurement": "",
        "precision": "",
        "retentionPolicy": "",
        "database": "database",
        "precisionV18FluxV20": "ms",
        "retentionPolicyV18Flux": "",
        "org": "organisation",
        "bucket": "bucket",
        "x": 510,
        "y": 1340,
        "wires": []
    },
    {
        "id": "25c59be20820f116",
        "type": "link out",
        "z": "0e992f61a706eb58",
        "g": "6d15c9fd9f5b6e7e",
        "name": "To Dashboard Live Feed",
        "mode": "link",
        "links": [
            "4fa12711f176e1bb"
        ],
        "x": 965,
        "y": 1380,
        "wires": []
    },
    {
        "id": "b98f28c74f086922",
        "type": "comment",
        "z": "0e992f61a706eb58",
        "g": "71c8aa3b6b346885",
        "name": "Alarm Control",
        "info": "",
        "x": 150,
        "y": 1120,
        "wires": []
    },
    {
        "id": "52c952ec42fbd7ca",
        "type": "comment",
        "z": "0e992f61a706eb58",
        "g": "c3bc344f2852449d",
        "name": "Alarm Tick",
        "info": "",
        "x": 680,
        "y": 1120,
        "wires": []
    },
    {
        "id": "b213f336912bac3c",
        "type": "comment",
        "z": "0e992f61a706eb58",
        "g": "6d15c9fd9f5b6e7e",
        "name": "Camera",
        "info": "",
        "x": 730,
        "y": 1300,
        "wires": []
    },
    {
        "id": "8cae70e72de3e1f6",
        "type": "comment",
        "z": "0e992f61a706eb58",
        "g": "7404463c72010353",
        "name": "Persistence",
        "info": "",
        "x": 150,
        "y": 1300,
        "wires": []
    },
    {
        "id": "be754b1a8f482a59",
        "type": "function",
        "z": "0e992f61a706eb58",
        "g": "aad72eeb907091b5",
        "name": "Build Alert MQTT Payload",
        "func": "/**\n * Convert detection output to the alert payload contract.\n */\nif (!msg.event) {\n    return null;\n}\n\nmsg.payload = msg.event;\nreturn msg;",
        "outputs": 1,
        "timeout": 0,
        "noerr": 0,
        "initialize": "",
        "finalize": "",
        "libs": [],
        "x": 2130,
        "y": 820,
        "wires": [
            [
                "87c6979873121a16"
            ]
        ]
    },
    {
        "id": "fe92c5eaa6430a56",
        "type": "function",
        "z": "0e992f61a706eb58",
        "g": "aad72eeb907091b5",
        "name": "Build Status MQTT Payload",
        "func": "/**\n * Convert detection output to the status payload contract.\n */\nif (!msg.statusUpdate) {\n    return null;\n}\n\nmsg.payload = msg.statusUpdate;\nreturn msg;",
        "outputs": 1,
        "timeout": 0,
        "noerr": 0,
        "initialize": "",
        "finalize": "",
        "libs": [],
        "x": 2140,
        "y": 880,
        "wires": [
            [
                "166ec84d0479edca"
            ]
        ]
    },
    {
        "id": "6426a2171f12d72f",
        "type": "http in",
        "z": "0e992f61a706eb58",
        "g": "2ceda20c5bfc9df6",
        "name": "GET /api/settings",
        "url": "/api/settings",
        "method": "get",
        "upload": false,
        "skipBodyParsing": false,
        "swaggerDoc": "",
        "x": 640,
        "y": 160,
        "wires": [
            [
                "0b3b7672f6522f91"
            ]
        ]
    },
    {
        "id": "b8e4c175ebf1cbce",
        "type": "http in",
        "z": "0e992f61a706eb58",
        "g": "76f49feef62a3798",
        "name": "POST /api/settings",
        "url": "/api/settings",
        "method": "post",
        "upload": false,
        "skipBodyParsing": false,
        "swaggerDoc": "",
        "x": 170,
        "y": 920,
        "wires": [
            [
                "977de577e811690b"
            ]
        ]
    },
    {
        "id": "1b3d7b866bb8db1a",
        "type": "function",
        "z": "0e992f61a706eb58",
        "g": "76f49feef62a3798",
        "name": "Update Settings",
        "func": "/**\n * Update configurable system settings.\n * Only approved settings are written back to flow context.\n */\nconst current = flow.get(\"settings\") || {};\nconst incoming = msg.payload || {};\n\nconst updated = {\n    ...current,\n    suspiciousModeEnabled: incoming.suspiciousModeEnabled !== undefined\n        ? Boolean(incoming.suspiciousModeEnabled)\n        : current.suspiciousModeEnabled,\n    seatDeltaCm: incoming.seatDeltaCm !== undefined\n        ? Number(incoming.seatDeltaCm)\n        : current.seatDeltaCm,\n    seatDebounceMs: incoming.seatDebounceMs !== undefined\n        ? Number(incoming.seatDebounceMs)\n        : current.seatDebounceMs,\n    soundSpike: incoming.soundSpike !== undefined\n        ? Number(incoming.soundSpike)\n        : current.soundSpike,\n    vibrationSpike: incoming.vibrationSpike !== undefined\n        ? Number(incoming.vibrationSpike)\n        : current.vibrationSpike,\n    accelMagSpike: incoming.accelMagSpike !== undefined\n        ? Number(incoming.accelMagSpike)\n        : current.accelMagSpike,\n    confirmWindowMs: incoming.confirmWindowMs !== undefined\n        ? Number(incoming.confirmWindowMs)\n        : current.confirmWindowMs,\n    suspiciousTimeoutMs: incoming.suspiciousTimeoutMs !== undefined\n        ? Number(incoming.suspiciousTimeoutMs)\n        : current.suspiciousTimeoutMs,\n    alarmMinMs: incoming.alarmMinMs !== undefined\n        ? Number(incoming.alarmMinMs)\n        : current.alarmMinMs,\n    autoResolveQuietMs: incoming.autoResolveQuietMs !== undefined\n        ? Number(incoming.autoResolveQuietMs)\n        : current.autoResolveQuietMs,\n    notificationPhone: incoming.notificationPhone ?? current.notificationPhone ?? \"\",\n    notificationEmail: incoming.notificationEmail ?? current.notificationEmail ?? \"\"\n};\n\nflow.set(\"settings\", updated);\n\nnode.send([\n    {\n        payload: {\n            ok: true,\n            settings: updated,\n            ts: Date.now()\n        }\n    },\n    {\n        topic: \"vehicle/security/settings\",\n        payload: {\n            settings: updated,\n            ts: Date.now()\n        }\n    }\n]);\n\nreturn null;",
        "outputs": 2,
        "timeout": 0,
        "noerr": 0,
        "initialize": "",
        "finalize": "",
        "libs": [],
        "x": 640,
        "y": 920,
        "wires": [
            [
                "ca2f6d1e9ece927b"
            ],
            [
                "e18476dae9472cd5"
            ]
        ]
    },
    {
        "id": "0b3b7672f6522f91",
        "type": "function",
        "z": "0e992f61a706eb58",
        "g": "2ceda20c5bfc9df6",
        "name": "Build Settings Response",
        "func": "/**\n * Return the current configurable system settings.\n */\nmsg.payload = {\n    ok: true,\n    settings: flow.get(\"settings\") || {},\n    ts: Date.now()\n};\n\nreturn msg;",
        "outputs": 1,
        "timeout": 0,
        "noerr": 0,
        "initialize": "",
        "finalize": "",
        "libs": [],
        "x": 870,
        "y": 160,
        "wires": [
            [
                "86b8ac629d80c35d"
            ]
        ]
    },
    {
        "id": "86b8ac629d80c35d",
        "type": "http response",
        "z": "0e992f61a706eb58",
        "g": "2ceda20c5bfc9df6",
        "name": "Settings GET Response",
        "statusCode": "",
        "headers": {},
        "x": 1130,
        "y": 160,
        "wires": []
    },
    {
        "id": "977de577e811690b",
        "type": "json",
        "z": "0e992f61a706eb58",
        "g": "76f49feef62a3798",
        "name": "Parse Settings Request",
        "property": "payload",
        "action": "obj",
        "pretty": false,
        "x": 410,
        "y": 920,
        "wires": [
            [
                "1b3d7b866bb8db1a"
            ]
        ]
    },
    {
        "id": "ca2f6d1e9ece927b",
        "type": "http response",
        "z": "0e992f61a706eb58",
        "g": "76f49feef62a3798",
        "name": "Settings POST Response",
        "statusCode": "",
        "headers": {},
        "x": 870,
        "y": 900,
        "wires": []
    },
    {
        "id": "e18476dae9472cd5",
        "type": "mqtt out",
        "z": "0e992f61a706eb58",
        "g": "76f49feef62a3798",
        "name": "Settings Status MQTT Out",
        "topic": "vehicle/security/settings",
        "qos": "1",
        "retain": "",
        "respTopic": "",
        "contentType": "",
        "userProps": "",
        "correl": "",
        "expiry": "",
        "broker": "mqtt_broker_pi1",
        "x": 880,
        "y": 940,
        "wires": []
    },
    {
        "id": "2d7dc0470413a8de",
        "type": "comment",
        "z": "0e992f61a706eb58",
        "g": "2ceda20c5bfc9df6",
        "name": "Settings",
        "info": "",
        "x": 620,
        "y": 120,
        "wires": []
    },
    {
        "id": "fdae73bae71188f3",
        "type": "comment",
        "z": "0e992f61a706eb58",
        "g": "76f49feef62a3798",
        "name": "Configure",
        "info": "",
        "x": 140,
        "y": 880,
        "wires": []
    },
    {
        "id": "b0cba382c50d09ab",
        "type": "function",
        "z": "0e992f61a706eb58",
        "g": "ce7e83e4ad2de9f6",
        "name": "Build Live Feed Response",
        "func": "/**\n * Return recent live feed events for the dashboard.\n */\nmsg.payload = {\n    ok: true,\n    events: flow.get(\"liveFeedEvents\") || [],\n    ts: Date.now()\n};\n\nreturn msg;",
        "outputs": 1,
        "timeout": 0,
        "noerr": 0,
        "initialize": "",
        "finalize": "",
        "libs": [],
        "x": 730,
        "y": 1520,
        "wires": [
            [
                "4f64cea803c823d3"
            ]
        ]
    },
    {
        "id": "6394a83cef5e60d3",
        "type": "http in",
        "z": "0e992f61a706eb58",
        "g": "ce7e83e4ad2de9f6",
        "name": "GET /api/live-feed",
        "url": "/api/live-feed",
        "method": "get",
        "upload": false,
        "skipBodyParsing": false,
        "swaggerDoc": "",
        "x": 490,
        "y": 1520,
        "wires": [
            [
                "b0cba382c50d09ab"
            ]
        ]
    },
    {
        "id": "4f64cea803c823d3",
        "type": "http response",
        "z": "0e992f61a706eb58",
        "g": "ce7e83e4ad2de9f6",
        "name": "Live Feed Response",
        "statusCode": "",
        "headers": {},
        "x": 980,
        "y": 1520,
        "wires": []
    },
    {
        "id": "e82b7cfb18701fc0",
        "type": "comment",
        "z": "0e992f61a706eb58",
        "g": "ce7e83e4ad2de9f6",
        "name": "HTTP Read",
        "info": "",
        "x": 470,
        "y": 1480,
        "wires": []
    },
    {
        "id": "4fa12711f176e1bb",
        "type": "link in",
        "z": "0e992f61a706eb58",
        "g": "2dc032b30fb2cdf3",
        "name": "Live Feed Event In",
        "links": [
            "1ba6a00a59d90dd3",
            "25c59be20820f116"
        ],
        "x": 95,
        "y": 1480,
        "wires": [
            [
                "dedbe14c1df4bd31"
            ]
        ]
    },
    {
        "id": "dedbe14c1df4bd31",
        "type": "function",
        "z": "0e992f61a706eb58",
        "g": "2dc032b30fb2cdf3",
        "name": "Store Live Feed Event",
        "func": "/**\n * Store recent live feed events for dashboard polling.\n * Keeps only the newest 50 events in memory.\n */\nconst event = msg.event || null;\nconst intrusion = flow.get(\"intrusion\") || {};\n\nif (!event) {\n    return null;\n}\n\nconst feed = flow.get(\"liveFeedEvents\") || [];\n\nconst entry = {\n    type: event.type || \"UNKNOWN\",\n    reason: event.reason || \"\",\n    intrusionId: event.intrusionId || null,\n    evidence: Array.isArray(event.evidence) ? event.evidence : [],\n    state: event.state || (flow.get(\"securityState\") || \"inactive\"),\n    picturePath: event.picturePath || intrusion.picturePath || \"\",\n    videoPath: event.videoPath || intrusion.videoPath || \"\",\n    note: event.note || \"\",\n    ts: event.ts || Date.now()\n};\n\nfeed.unshift(entry);\n\nflow.set(\"liveFeedEvents\", feed.slice(0, 50));\n\nreturn null;",
        "outputs": 1,
        "timeout": 0,
        "noerr": 0,
        "initialize": "",
        "finalize": "",
        "libs": [],
        "x": 240,
        "y": 1480,
        "wires": [
            []
        ]
    },
    {
        "id": "e977007d93a70419",
        "type": "comment",
        "z": "0e992f61a706eb58",
        "g": "2dc032b30fb2cdf3",
        "name": "Event Storage",
        "info": "",
        "x": 150,
        "y": 1440,
        "wires": []
    },
    {
        "id": "e56f211f1a234d45",
        "type": "link out",
        "z": "0e992f61a706eb58",
        "g": "aad72eeb907091b5",
        "name": "To Event Persistence",
        "mode": "link",
        "links": [
            "9920a4a96963e478"
        ],
        "x": 1955,
        "y": 820,
        "wires": []
    },
    {
        "id": "0ee56e928c0e6155",
        "type": "debug",
        "z": "0e992f61a706eb58",
        "g": "6d15c9fd9f5b6e7e",
        "name": "debugCamera",
        "active": true,
        "tosidebar": true,
        "console": false,
        "tostatus": false,
        "complete": "true",
        "targetType": "full",
        "statusVal": "",
        "statusType": "auto",
        "x": 1240,
        "y": 1340,
        "wires": []
    },
    {
        "id": "93a285a031db5877",
        "type": "link in",
        "z": "0e992f61a706eb58",
        "g": "6d15c9fd9f5b6e7e",
        "name": "Camera Event In",
        "links": [
            "f3b5737469a0ae23"
        ],
        "x": 715,
        "y": 1380,
        "wires": [
            [
                "a2e2b9722d48755b"
            ]
        ]
    },
    {
        "id": "f3b5737469a0ae23",
        "type": "link out",
        "z": "0e992f61a706eb58",
        "g": "aad72eeb907091b5",
        "name": "To Camera Event",
        "mode": "link",
        "links": [
            "93a285a031db5877"
        ],
        "x": 1955,
        "y": 780,
        "wires": []
    },
    {
        "id": "ad1c7710ab01be2b",
        "type": "debug",
        "z": "0e992f61a706eb58",
        "g": "6d15c9fd9f5b6e7e",
        "name": "debugCameraCommand",
        "active": true,
        "tosidebar": true,
        "console": false,
        "tostatus": false,
        "complete": "true",
        "targetType": "full",
        "statusVal": "",
        "statusType": "auto",
        "x": 1050,
        "y": 1300,
        "wires": []
    },
    {
        "id": "3f49b68e543d0680",
        "type": "http in",
        "z": "0e992f61a706eb58",
        "g": "ddbc521e6b96d5b1",
        "name": "GET /media/images/:filename",
        "url": "/media/images/:filename",
        "method": "get",
        "upload": false,
        "skipBodyParsing": false,
        "swaggerDoc": "",
        "x": 1580,
        "y": 1120,
        "wires": [
            [
                "fa89397cc634bc5a"
            ]
        ]
    },
    {
        "id": "fa89397cc634bc5a",
        "type": "function",
        "z": "0e992f61a706eb58",
        "g": "ddbc521e6b96d5b1",
        "name": "Build Image File Path",
        "func": "/**\n * Build the absolute path for an image request.\n * Only allows safe filenames to prevent path traversal.\n *\n * Outputs:\n * 1 = valid file read request\n * 2 = immediate HTTP error response\n */\nconst filename = msg.req?.params?.filename || \"\";\n\n// Allow only simple filenames such as:\n// intr_1773108166477.jpg\nif (!/^[a-zA-Z0-9._-]+$/.test(filename)) {\n    msg.statusCode = 400;\n    msg.headers = {\n        \"Content-Type\": \"application/json\"\n    };\n    msg.payload = {\n        ok: false,\n        error: \"Invalid filename\"\n    };\n    return [null, msg];\n}\n\nmsg.filename = \"/home/pi/autoguard/images/\" + filename;\nmsg.requestedFile = filename;\n\nreturn [msg, null];",
        "outputs": 2,
        "timeout": 0,
        "noerr": 0,
        "initialize": "",
        "finalize": "",
        "libs": [],
        "x": 1840,
        "y": 1120,
        "wires": [
            [
                "7baa995010645c42"
            ],
            [
                "fbd399cdde11bdfe"
            ]
        ]
    },
    {
        "id": "7baa995010645c42",
        "type": "file in",
        "z": "0e992f61a706eb58",
        "g": "ddbc521e6b96d5b1",
        "name": "Read Image File",
        "filename": "filename",
        "filenameType": "msg",
        "format": "",
        "chunk": false,
        "sendError": false,
        "encoding": "none",
        "allProps": false,
        "x": 2060,
        "y": 1080,
        "wires": [
            [
                "2c583a3f351f9514"
            ]
        ]
    },
    {
        "id": "2c583a3f351f9514",
        "type": "function",
        "z": "0e992f61a706eb58",
        "g": "ddbc521e6b96d5b1",
        "name": "Build Image Response",
        "func": "/**\n * Return image bytes with the correct content type.\n */\nconst filename = msg.requestedFile || msg.filename || \"\";\n\nlet contentType = \"application/octet-stream\";\n\nif (filename.endsWith(\".jpg\") || filename.endsWith(\".jpeg\")) {\n    contentType = \"image/jpeg\";\n} else if (filename.endsWith(\".png\")) {\n    contentType = \"image/png\";\n} else if (filename.endsWith(\".webp\")) {\n    contentType = \"image/webp\";\n}\n\nmsg.headers = {\n    \"Content-Type\": contentType,\n    \"Cache-Control\": \"no-cache\"\n};\n\nreturn msg;",
        "outputs": 1,
        "timeout": 0,
        "noerr": 0,
        "initialize": "",
        "finalize": "",
        "libs": [],
        "x": 2280,
        "y": 1080,
        "wires": [
            [
                "fbd399cdde11bdfe"
            ]
        ]
    },
    {
        "id": "fbd399cdde11bdfe",
        "type": "http response",
        "z": "0e992f61a706eb58",
        "g": "ddbc521e6b96d5b1",
        "name": "Image Response",
        "statusCode": "",
        "headers": {},
        "x": 2510,
        "y": 1120,
        "wires": []
    },
    {
        "id": "2e682f79be89001d",
        "type": "comment",
        "z": "0e992f61a706eb58",
        "g": "ddbc521e6b96d5b1",
        "name": "View Image",
        "info": "",
        "x": 1530,
        "y": 1080,
        "wires": []
    },
    {
        "id": "ea1ba8dc9c893984",
        "type": "catch",
        "z": "0e992f61a706eb58",
        "g": "d6f33d740f37f66b",
        "name": "Catch Media Errors",
        "scope": [
            "7baa995010645c42",
            "eccc694b470a9fd3"
        ],
        "uncaught": false,
        "x": 1550,
        "y": 1400,
        "wires": [
            [
                "a95d6e9cb54b0e9e"
            ]
        ]
    },
    {
        "id": "a95d6e9cb54b0e9e",
        "type": "function",
        "z": "0e992f61a706eb58",
        "g": "d6f33d740f37f66b",
        "name": "Build Media Error Response",
        "func": "/**\n * Return a clean JSON error response for media read failures.\n */\nmsg.statusCode = 404;\nmsg.headers = {\n    \"Content-Type\": \"application/json\"\n};\n\nmsg.payload = {\n    ok: false,\n    error: \"Media file not found\",\n    details: msg.error?.message || \"Unknown media error\"\n};\n\nreturn msg;",
        "outputs": 1,
        "timeout": 0,
        "noerr": 0,
        "initialize": "",
        "finalize": "",
        "libs": [],
        "x": 1800,
        "y": 1400,
        "wires": [
            [
                "dbb8f9c1e900f0d1"
            ]
        ]
    },
    {
        "id": "dbb8f9c1e900f0d1",
        "type": "http response",
        "z": "0e992f61a706eb58",
        "g": "d6f33d740f37f66b",
        "name": "Media Error Response",
        "statusCode": "",
        "headers": {},
        "x": 2060,
        "y": 1400,
        "wires": []
    },
    {
        "id": "4f97c6f6862eb0f4",
        "type": "comment",
        "z": "0e992f61a706eb58",
        "g": "d6f33d740f37f66b",
        "name": "Catch Media Error",
        "info": "",
        "x": 1550,
        "y": 1360,
        "wires": []
    },
    {
        "id": "af72f5122aab46ee",
        "type": "http in",
        "z": "0e992f61a706eb58",
        "g": "3053a935888cd15a",
        "name": "GET /media/videos/:filename",
        "url": "/media/videos/:filename",
        "method": "get",
        "upload": false,
        "skipBodyParsing": false,
        "swaggerDoc": "",
        "x": 1580,
        "y": 1260,
        "wires": [
            [
                "a288150cbe49f92f"
            ]
        ]
    },
    {
        "id": "ea3ea16e0f56fd3f",
        "type": "comment",
        "z": "0e992f61a706eb58",
        "g": "3053a935888cd15a",
        "name": "View Video",
        "info": "",
        "x": 1520,
        "y": 1220,
        "wires": []
    },
    {
        "id": "a288150cbe49f92f",
        "type": "function",
        "z": "0e992f61a706eb58",
        "g": "3053a935888cd15a",
        "name": "Build Video File Path",
        "func": "/**\n * Build the absolute path for a video request.\n * Only allows safe filenames to prevent path traversal.\n *\n * Outputs:\n * 1 = valid file read request\n * 2 = immediate HTTP error response\n */\nconst filename = msg.req?.params?.filename || \"\";\n\nif (!/^[a-zA-Z0-9._-]+$/.test(filename)) {\n    msg.statusCode = 400;\n    msg.headers = {\n        \"Content-Type\": \"application/json\"\n    };\n    msg.payload = {\n        ok: false,\n        error: \"Invalid filename\"\n    };\n    return [null, msg];\n}\n\nmsg.filename = \"/home/pi/autoguard/videos/\" + filename;\nmsg.requestedFile = filename;\n\nreturn [msg, null];",
        "outputs": 2,
        "timeout": 0,
        "noerr": 0,
        "initialize": "",
        "finalize": "",
        "libs": [],
        "x": 1840,
        "y": 1260,
        "wires": [
            [
                "eccc694b470a9fd3"
            ],
            [
                "ba19471e9916b696"
            ]
        ]
    },
    {
        "id": "eccc694b470a9fd3",
        "type": "file in",
        "z": "0e992f61a706eb58",
        "g": "3053a935888cd15a",
        "name": "Read Video File",
        "filename": "filename",
        "filenameType": "msg",
        "format": "",
        "chunk": false,
        "sendError": false,
        "encoding": "none",
        "allProps": false,
        "x": 2060,
        "y": 1220,
        "wires": [
            [
                "5df517086efdfe47"
            ]
        ]
    },
    {
        "id": "5df517086efdfe47",
        "type": "function",
        "z": "0e992f61a706eb58",
        "g": "3053a935888cd15a",
        "name": "Build Video Response",
        "func": "/**\n * Return video bytes with the correct content type.\n */\nconst filename = msg.requestedFile || msg.filename || \"\";\n\nlet contentType = \"application/octet-stream\";\n\nif (filename.endsWith(\".mp4\")) {\n    contentType = \"video/mp4\";\n} else if (filename.endsWith(\".webm\")) {\n    contentType = \"video/webm\";\n} else if (filename.endsWith(\".ogg\")) {\n    contentType = \"video/ogg\";\n}\n\nmsg.headers = {\n    \"Content-Type\": contentType,\n    \"Cache-Control\": \"no-cache\",\n    \"Content-Disposition\": \"inline\"\n};\n\nreturn msg;",
        "outputs": 1,
        "timeout": 0,
        "noerr": 0,
        "initialize": "",
        "finalize": "",
        "libs": [],
        "x": 2280,
        "y": 1220,
        "wires": [
            [
                "ba19471e9916b696"
            ]
        ]
    },
    {
        "id": "ba19471e9916b696",
        "type": "http response",
        "z": "0e992f61a706eb58",
        "g": "3053a935888cd15a",
        "name": "Video Response",
        "statusCode": "",
        "headers": {},
        "x": 2500,
        "y": 1260,
        "wires": []
    },
    {
        "id": "0299c5d668ee9060",
        "type": "comment",
        "z": "0e992f61a706eb58",
        "g": "9379380a7711d644",
        "name": "",
        "info": "",
        "x": 1500,
        "y": 1020,
        "wires": []
    }
]